<?xml version="1.0" encoding="utf-8"?>
<document>

    <pageMeta>
        <pageTitle>
            <en>Food Inspection Services &amp; Quality Control in Food Industry | AsiaInspection – Product Safety &amp; Compliance</en>
            <ar>خدمات التفتيش على الأغذية | AsiaInspection - ضمان الجودة، السلامة والمطابقة</ar>
            <fr>Services d'inspection des denrées alimentaires| AsiaInspection - Assurance qualité, sécurité et conformité</fr>
            <de>Lebensmittelinspektionsdienste | AsiaInspection – Qualitätssicherung, Sicherheit &amp; Konformität</de>
            <es>Servicios de inspección alimentaria | AsiaInspection - Garantía de calidad, seguridad y cumplimiento</es>
            <zh>食品检验服务|AsiaInspection-保障质量、安全及合规性</zh>
            <tr>Gıda Muayene Hizmetleri ve Gıda Endüstrisinde Kalite Kontrol | AsiaInspection – Ürün Güvenliği ve Uygunluk</tr>
            <pt>Serviços de Inspeção Alimentar e Controlo Qualidade na Indústria Alimentar | AsiaInspection - Segurança do Produto e Conformidade</pt>
            <ru>Услуги по инспекции пищевых товаров и контроль качества в пищевой промышленности | AsiaInspection – Безопасность продукции и соответствие нормам</ru>
            <it>Servizi di Ispezione Alimentare e Controllo della Qualità nell'Industria Alimentare | AsiaInspection - Conformità e Sicurezza del Prodotto</it>
        </pageTitle>
        <pageDesc>
            <en>AsiaInspection offers food inspection and quality control services, helping you ensure the safety of your products. See why we’re the trusted service for inspections and audits around the world.</en>
            <ar>تُقدم AsiaInspection خدمات التفتيش على الأغذية في كافة أنحاء العالم. لمعرفة المزيد حول عمليات التفتيش وخدمات مراقبة الجودة التي نقوم بها.</ar>
            <fr>AsiaInspection propose des services d'inspection des denrées alimentaires dans le monde entier. Découvrez nos services d'inspection et de contrôle de la qualité</fr>
            <de>AsiaInspection bietet Lebensmittelinspektionsdienste auf weltweiter Ebene an. Erfahren Sie mehr über unsere Inspektions- und Qualitätskontrolldienste.</de>
            <es>AsiaInspection ofrece servicios de inspección alimentaria en todo el mundo. Más información acerca de nuestros servicios de inspección y control de calidad.</es>
            <zh>AI亚检在全世界范围内提供食品检验服务。了解更多关于我们的检验和质量控制服务。</zh>
            <tr>AsiaInspection ürünlerinizin güvenliğini sağlamanıza yardımcı olarak gıda muayenesi ve kalite kontrol hizmetleri sunar. Dünya çapındaki muayene ve denetimlerde neden güvenilir bir hizmet olduğumuza bakın.</tr>
            <pt>A AsiaInspection oferece serviços de inspeção alimentares e serviços de controlo de qualidade, ajudando-o a garantir a segurança dos seus produtos. Veja porque somos o serviço de confiança para inspeções e auditorias por todo o mundo.</pt>
            <ru>AsiaInspection предлагает инспекцию пищевых товаров и услуги по контролю качества, помогая вам обеспечить безопасность вашей продукции. Узнайте, почему нашим услугам в области инспекции и аудита доверяют во всем мире.</ru>
            <it>AsiaInspection fornisce servizi di ispezione alimentare e controllo della qualità, per aiutarti a garantire la sicurezza dei tuoi prodotti. Scopri perché si affidano al nostro servizio per ispezioni e audit in tutto il mondo.</it>
        </pageDesc>
        <pageKeywords>
            <en>food inspection services, quality control in food industry, food quality and safety</en>
            <ar>التفتيش على الأغذية، اختبار الأغذية، مراقبة جودة الأغذية</ar>
            <fr>Inspection des denrées alimentaires, test de denrées alimentaires, Contrôle de la qualité des denrées alimentaires</fr>
            <de>Lebensmittelinspektion, Lebensmittelprüfung, Lebensmittelqualitätskontrolle</de>
            <es>Inspección alimentaria, Análisis de alimentos, Control de calidad de los alimentos</es>
            <zh>食品检验、食品检测、食品质量控制</zh>
            <tr>gıda muayene hizmetleri, gıda endüstrisinde kalite kontrol, gıda kalite ve güvenliği</tr>
            <pt>serviços inspeção alimentar, controlo qualidade na indústria alimentar, qualidade e segurança alimentar</pt>
            <ru>услуги продуктовой инспекции, контроль качества в пищевой промышленности, качество и безопасность продовольственных товаров</ru>
            <it>servizi di ispezione alimentare, controllo della qualità nell'industria alimentare, qualità e sicurezza degli aliment</it>
        </pageKeywords>
    </pageMeta>

    <en>
        <title>Food Inspection Services</title>
        <subtext>
            <![CDATA[
            <p class="pwhite">AsiaInspection offers food inspection services globally, helping you ensure the quality and safety of your food products before they leave the factory.</p>
            ]]>
        </subtext>
        <subtext2title>Food Inspections &amp; Quality Control</subtext2title>
        <subtext2>
            <![CDATA[
            <p>In a world where food products often travel thousands of miles before reaching the consumer, safeguarding the quality and safety of your food is paramount at every stage. Professional food inspections give you an accurate picture of your product’s state before it is shipped, as well as upon arrival at the destination.</p>
            <p>AI’s food inspections allow you to spot inconsistencies in your production lots before they leave the farm or factory, helping you react timely and avoid costly rework, sorting or recalls. With detailed inspection reports delivered the same day and real-time data intelligence on your suppliers, you can make fast and informed decisions for your food supply chain.</p>]]>
        </subtext2>
        <subtext3title>Food Inspections Expertise</subtext3title>
        <subtext3>
            <![CDATA[
            AI offers fast and reliable product inspection services in the following categories:<br/>
            <table border="0" width="100%">
                <tr>
                    <td width="50%">
                        <ul style="margin:0px;">
                            <li><a href="/testing/seafood">Seafood</a>, <a href="/testing/meat-poultry">meat and poultry</a></li>
                            <li><a href="/testing/produce-inspections-and-quality-control">Fresh produce</a></li>
                        </ul>
                    </td>
                    <td width="50%">
                        <ul style="margin:0px;">
                            <li><a href="/testing/quality-control-for-processed-food">Processed food</a></li>
                            <li><a href="/testing/food-packaging-and-containers">Food containers</a></li>
                        </ul>
                    </td>
                </tr>
            </table><br/>
            When your product is ready to be inspected, one of AI’s professional inspectors will visit your supplier and check the quantity, packing, labeling, dimensions, weight, and visual characteristics of a randomly selected sample. In our inspections, we follow the guidelines of the World Health Organization Food Code and use the internationally recognized ANSI/ASQC Z1.4 (ISO 2859-1) statistical sampling procedure. This guarantees that we check a sample that properly represents your food production lot, and not a sample your supplier wants you to check.
            <br/><br/>
            Our product inspectors are highly experienced in their respective areas of specialization, which include <a href="/testing/produce-inspections-and-quality-control">Fresh Produce</a>, <a href="/testing/quality-control-for-processed-food">Processed Foods</a>, <a href="/testing/food-packaging-and-containers">Food Containers</a>, <a href="/testing/seafood">Seafood</a>, <a href="/testing/meat-poultry">Meat</a>, and <a href="/testing/meat-poultry">Poultry</a>, and others. During inspections, they follow detailed inspection protocols prepared by our experts. AI’s food inspection protocols merge your instructions and specifications with industry standards and our extensive know-how, ensuring a comprehensive check of your food products’ quality, safety, and compliance.
            ]]>
        </subtext3>
        <subtext4title>Food Inspections Process</subtext4title>
        <subtext4>
            <![CDATA[
            <strong>1. Booking:</strong> using your online account or the <a href="/app">AI mobile app</a>, you can book your food inspection quickly and easily. Our user-friendly booking forms will guide you through the process, making sure you include all key specifications of your order, such as:
            <br/>
            <ul class="marginzero">
                <li>Factory contact detail</li>
                <li>Product description</li>
                <li>Pictures</li>
                <li>Key tests to perform on-site</li>
                <li>Defects to look for</li>
                <li>Sampling method</li>
            </ul>
            <p>You will receive a price quote for your food inspection immediately after placing the order.</p>
            <br/>

            <strong>2. Processing:</strong> our team will liaise with your supplier to confirm the date and place of the inspection, while our experts prepare a comprehensive food inspection protocol for our inspector to follow.
            <br/><br/>
            <p>Change of plans? Not a problem: you can reschedule or cancel your order until 4 pm of the day before the inspection.</p>
            <br/>

            <p><strong>3. Inspection:</strong> on the day of the food inspection, an AI inspector will visit your supplier’s facility and carry out such standardized steps as:</p>
            <ul class="marginzero">
                <li>Random sampling (determined according to product type)</li>
                <li>Visual check</li>
                <li>Product-specific tests</li>
                <li>Defect sorting and counting</li>
                <li>Packing and labeling check</li>
            </ul>
            <br/>

            <strong>4. Report delivery:</strong> a detailed food inspection report with photographs will be sent to you on the same day, letting you make an informed decision regarding the shipment of your lot.
            ]]>
            </subtext4>
        <subtext5title>Why Perform a Food Inspection?</subtext5title>
        <subtext5><![CDATA[
            <ul class="marginzero">
                <li>To safeguard the quality and safety of your food product at every stage</li>
                <li>To identify any potential damage during transit</li>
                <li>To maintain consumer confidence and brand reputation</li>
                <li>To avoid safety recalls</li>
                <li>To comply with statutory regulations and standards of your destination market</li>
            </ul>
            ]]></subtext5>
        <whyUsTitle>Why AsiaInspection</whyUsTitle>
        <whyUsList>
            <li><![CDATA[${{priceIA}} USD all-inclusive per man-day]]></li>
            <li><![CDATA[An inspector onsite within 48 hours<sup class="hoverText" cargo="txtAuditor"><a href="javascript://">[1]</a></sup> and same day reports<sup class="hoverText" cargo="txtSameDayAudit"><a href="javascript://">[2]</a></sup>]]></li>
            <li>Easy online scheduling with customizable checklists</li>
        </whyUsList>
        <hoverOne>
            <![CDATA[AsiaInspection guarantees to have an inspector or auditor ready to be at the factory within 48 hours.<br /><br />This timeframe does not, however, guarantee factory preparedness or cooperation with AsiaInspection. Nor does it guarantee against limiting factors out of the control of AsiaInspection, such as transportation delays, or any event considered an Act of God.]]>
        </hoverOne>
        <hoverTwo>
            80% of all audit reports are delivered the same day. Reports being delivered the same day are contingent upon full factory cooperation.
        </hoverTwo>
        <schedButton url="/register">Get Started</schedButton>
    </en>

    <ar>
        <title>التفتيش على الأغذية</title>
        <subtext>
            <![CDATA[
            <p class="pwhite">تُقدم AsiaInspection خدمات التفتيش على الأغذية في كافة أنحاء العالم، لتساعدكم في ضمان جودة منتجاتك الغذائية وسلامتها قبل مغادرة المصنع.</p>
            <p class="pwhite">تُتيح لكم عمليات التفتيش على الأغذية التي تقوم بها AI باكتشاف أوجه التضارب في طلبيات منتجاتكم قبل مغادرة المزرعة أو المصنع، مما يسمح لكم بالتفاعل في الوقت المناسب وتجنب التكاليف الناتجة عن إعادة العمل أو الفرز أو الاستدعاء.  بإمكانكم اتخاذ قرارات سريعة ومستنيرة في أي مرحلة من مراحل سلسلة التوريد الغذائية بفضل تقارير التفتيش المُفصلة التي تُسلم في نفس اليوم بالإضافة إلى جمع البيانات الفورية حول الموردين.</p>
            ]]>
        </subtext>
        <subtext3title>الخبرة في مجال التفتيش على الأغذية</subtext3title>
        <subtext3>
            <![CDATA[
            تُقدم AI خدمات التفتيش على المنتجات تتسم بالسرعة والمصداقية في الفئات التالية:
            <br/>
            <table border="0" width="100%">
                <tr>
                    <td width="50%">
                        <ul style="margin:0px;">
                            <li><a href="/testing/seafood">
                                    المأكولات البحرية،
                            </a>, <a href="/testing/meat-poultry">
                          اللحوم والدواجن
                    </a></li>
                            <li><a href="/testing/produce-inspections-and-quality-control">
                                    المحاصيل الطازجة

                            </a></li>
                        </ul>
                    </td>
                    <td width="50%">
                        <ul style="margin:0px;">
                            <li><a href="/testing/quality-control-for-processed-food">الأغذية المُصنًعة</a></li>
                            <li><a href="/testing/food-packaging-and-containers">حاويات الأغذية</a></li>
                        </ul>
                    </td>
                </tr>
            </table><br/>
            عندما تصبح منتجاتكم جاهزة للتفتيش، سوف يزور أحد مفتشي AI المحترفين المورد ويختار عينة عشوائية ثم يتحقق من الكمية والتغليف والمُلصق والأبعاد والوزن بالإضافة إلى الخصائص البصرية. نتبع المبادئ التوجيهية للدستور الغذائي الذي أصدرته منظمة الصحة العالمية في عمليات التفتيش التي نقوم بها، كما نستخدم اجراءات أخذ العينات الإحصائية ANSI/ASQC Z1.4 (ISO 2859-1) المُعترف بها دوليًا. وهذا يضمن أننا سوف نفحص عينة تمثل بشكل سليم طلبية المنتجات الغذائية الخاصة بكم وليست أي عينة يرغب المورد في أن نقوم بفحصها.

            <br/><br/>
            يتمتع مفتشو المنتجات التابعون لنا بخبرة عالية في مجالات تخصصاتهم والتي تشمل المحاصيل الطازجة والأغذية المُصنعة وحاويات الأغذية والمأكولات البحرية واللحوم والدواجن وغيرها. وخلال عمليات التفتيش، يتبع المفتشون بروتوكولات التفتيش المُفصلة التي أعدها خبراؤنا. تجمع بروتوكولات AI للتفتيش على الأغذية بين التعليمات والمواصفات الخاصة بكم وبين المعايير الصناعية وخبرتنا الواسعة، مما يضمن فحصًا شاملًا لجودة منتجاتكم الغذائية وسلامتها ومطابقتها.

            ]]>
        </subtext3>
        <subtext4title>عملية التفتيش على الأغذية</subtext4title>
        <subtext4>
            <![CDATA[
            <strong>1. الحجز: يمكنك حجز عملية التفتيش على الأغذية بسهولة ويُسر باستخدام حسابك على موقعنا الإلكتروني أو تطبيق AI للهواتف الذكية.  سوف تُرشدك استمارات الحجز سهلة الاستخدام خلال تلك العملية، كي نضمن إدخالك لجميع المواصفات الرئيسة لطلبك مثل:</strong>
            <br/>
            <ul class="marginzero">
                <li>عناوين الاتصال بالمصنع</li>
                <li>وصف المنتج</li>
                <li>الصور</li>
                <li>الاختبارات الرئيسة التي يجب القيام بها في الموقع</li>
                <li>العيوب التي ينبغي البحث عنها</li>
                <li>طريقة أخذ العينات</li>
            </ul>
            <p>سوف تستلم عرض أسعار لعملية التفتيش على الغذاء مباشرةً بعد إتمام الطلبية.</p>
            <br/>
            <strong>2. عملية المعالجة: سوف يتواصل فريقنا مع المورد لتأكيد تاريخ ومكان عملية التفتيش، في حين سيقوم خبراؤنا بتجهيز البروتوكول الشامل للتفتيش على الأغذية كي يتبعه مفتشنا.</strong>
            <br/><br/>
            <p>هل ترغب في تغيير الخطة؟ لا توجد مشكلة: يمكنك إعادة جدولة الطلبية أو إلغائها حتى الساعة الرابعة مساءً من اليوم السابق لعملية التفتيش.</p>
            <br/>
            <p><strong>3. التفتيش: في اليوم المُخصص لعملية التفتيش على الأغذية، سوف يزور أحد مفتشي AI مقر المورد ويقوم بتلك الخطوات القياسية على النحو التالي:</strong></p>
            <ul class="marginzero">
                <li>جمع العينة العشوائية (تُحدد وفقًا لنوع المنتج)</li>
                <li>الفحص البصري</li>
                <li>الاختبارات الخاصة بالمنتج</li>
                <li>فرز العيوب وعدها</li>
                <li>فحص التغليف والمُلصقات</li>
            </ul>
            <br/>
            <strong>4. تقديم التقرير: سوف يُرسل تقرير مفصل ومدعوم بالصور عن عملية التفتيش على الأغذية إليكم في نفس اليوم، مما يُمكنكم من اتخاذ قرارات مستنيرة بخصوص شحن طلبيتك.</strong>
            ]]>
            </subtext4>
        <subtext5title>لماذا تحتاجون إلى التفتيش على الأغذية؟</subtext5title>
        <subtext5><![CDATA[
            <ul class="marginzero">
                <li>للحفاظ على جودة منتجاتكم الغذائية وسلامتها في جميع المراحل</li>
                <li>لتحديد أي أضرار محتملة خلال عملية النقل</li>
                <li>للحفاظ على ثقة المستهلك وسمعة العلامة التجارية</li>
                <li>لتجنب استدعاء المنتجات نظرًا لمخاوف السلامة</li>
                <li>للامتثال مع اللوائح القانونية ومعايير السوق المُستهدف</li>
            </ul>
            ]]></subtext5>
        <whyUsTitle>لماذا AsiaInspection؟</whyUsTitle>
        <whyUsList>
            <li><![CDATA[${{priceIA}} USD all-inclusive per man-day]]></li>
            <li><![CDATA[An inspector onsite within 48 hours<sup class="hoverText" cargo="txtAuditor"><a href="javascript://">[1]</a></sup> and same day reports<sup class="hoverText" cargo="txtSameDayAudit"><a href="javascript://">[2]</a></sup>]]></li>
            <li>Easy online scheduling with customizable checklists</li>
        </whyUsList>
        <hoverOne>
            <![CDATA[AsiaInspection guarantees to have an inspector or auditor ready to be at the factory within 48 hours.<br /><br />This timeframe does not, however, guarantee factory preparedness or cooperation with AsiaInspection. Nor does it guarantee against limiting factors out of the control of AsiaInspection, such as transportation delays, or any event considered an Act of God.]]>
        </hoverOne>
        <hoverTwo>
            80% of all audit reports are delivered the same day. Reports being delivered the same day are contingent upon full factory cooperation.
        </hoverTwo>
        <schedButton url="/register">Get Started</schedButton>
    </ar>

    <fr>
        <title>Inspections des aliments</title>
        <subtext>
            <![CDATA[
            <p class="pwhite">AsiaInspection propose des services d'inspection d'aliments à l'échelle mondiale, et vous permet de garantir la qualité et la sécurité de vos produits alimentaires avant qu'ils ne quittent l'usine.</p>
            ]]>
        </subtext>
        <subtext2title>Inspections des aliments</subtext2title>
        <subtext2>
            <![CDATA[
            <p>Dans un monde où les produits alimentaires font souvent des milliers de kilomètres avant d'atteindre le consommateur, garantir la qualité et la sécurité de vos aliments est primordial à chaque étape. Les inspections professionnelles des denrées alimentaires vous donnent une image précise de l'état de votre produit avant son expédition, ainsi qu'à l'arrivée à destination.</p>
            <p>Les inspections des denrées alimentaires d'AI vous permettent de repérer les incohérences dans vos lots de production avant qu'ils ne quittent la ferme ou l'usine, vous permettant ainsi de réagir en temps opportun et d'éviter les reprises, le triage ou les rappels coûteux. Grâce à des rapports d'inspection détaillés livrés le jour même et à des informations en temps réel sur vos fournisseurs, vous pouvez prendre des décisions rapides et éclairées pour votre chaîne d'approvisionnement alimentaire.</p>]]
        </subtext2>
        <subtext3title>Expertise en inspection des denrées alimentaires</subtext3title>
        <subtext3>
            <![CDATA[
            AI propose des services d'inspection rapides et fiables de produits  dans les catégories suivantes :<br/>
            <table border="0" width="100%">
                <tr>
                    <td width="50%">
                        <ul style="margin:0px;">
                            <li><a href="/testing/seafood">Fruits de mer</a>, <a href="/testing/meat-poultry">viande et volaille</a></li>
                            <li><a href="/testing/produce">Produits frais</a></li>
                        </ul>
                    </td>
                    <td width="50%">
                        <ul style="margin:0px;">
                            <li><a href="/testing/processed-food">Aliment transformé</a></li>
                            <li><a href="/testing/food-containers">contenants pour aliments</a></li>
                        </ul>
                    </td>
                </tr>
            </table><br/>
            Lorsque votre produit est prêt à être inspecté, l'un des inspecteurs professionnels d'AI se rendra chez votre fournisseur et vérifiera la quantité, l'emballage, l'étiquetage, les dimensions, le poids et les caractéristiques visuelles d'un échantillon sélectionné au hasard. Dans nos inspections, nous suivons les directives du Code alimentaire de l'Organisation mondiale de la santé et nous utilisons la procédure d'échantillonnage statistiques ANSI / ASQC Z1.4 (ISO 2859-1) reconnue à l'échelle internationale. Celle-ci garantit que nous vérifions un échantillon qui représente correctement votre lot de production alimentaire et non pas un échantillon choisi par votre fournisseur.
            <br/><br/>
            Nos inspecteurs de produits sont très expérimentés dans leurs domaines respectifs de spécialisation, qui comprennent <a href="/testing/produce"> les produits frais,</a>, <a href="/testing/processed-food"> les aliments transformés</a>, <a href="/testing/food-containers"> les contenants alimentaires</a>, <a href="/testing/seafood"> les fruits de mer</a>, <a href="/testing/meat-poultry"> la viande et la volaille</a>, and <a href="/testing/meat-poultry">et bien</a> d'autres. Pendant les inspections, ils suivent des protocoles d'inspection détaillés préparés par nos experts. Les protocoles d'inspection de denrées alimentaires d'AI fusionnent vos instructions et vos spécifications avec les normes de l'industrie et notre important savoir-faire, assurant un contrôle exhaustif de la qualité, de la sécurité et de la conformité de vos produits alimentaires.
            ]]>
        </subtext2>
        <subtext4title>Processus d'inspection des denrées alimentaires</subtext4title>
        <subtext4>
            <![CDATA[
            <strong>1. Réservation:</strong> en utilisant votre compte en ligne ou <a href="/app">ligne ouion mobile AI</a>,  vous pouvez réserver votre inspection de denrées  alimentaires rapidement et facilement. Nos formulaires de réservation conviviaux vous guideront tout au long du processus, en veillant à ce que vous puissiez inclure toutes les spécifications importantes de votre commande, telles que :
            <br/>
            <ul class="marginzero">
                <li>Les coordonnées de l'usine</li>
                <li>La description du produit</li>
                <li>Des images</li>
                <li>Les tests essentiels à effectuer sur place</li>
                <li>Les anomalies à rechercher</li>
                <li>La méthode d'échantillonnage</li>
            </ul>
            <p>Vous recevrez un devis pour l'inspection de vos denrées alimentaires immédiatement après avoir passé la commande.</p>
            <br/>

            <strong>2. Traitement:</strong> notre équipe assure la liaison avec votre fournisseur pour confirmer la date et le lieu de l'inspection, tandis que nos experts préparent un protocole complet d'inspection des denrées alimentaires qui doit être suivi par notre inspecteur.
            <br/><br/>
            <p>Vous changez de plan ? Pas de problème : vous pouvez reporter ou annuler votre commande jusqu'à 16 heures de la journée avant l'inspection.</p>
            <br/>

            <p><strong>3. Inspection:</strong>  le jour de l'inspection des denrées alimentaires, un inspecteur de l'IA visitera l'installation de votre fournisseur et effectuera les étapes normalisées suivantes :</p>
            <ul class="marginzero">
                <li>Échantillonnage aléatoire (déterminé en fonction du type de produit)</li>
                <li>Contrôle visuel</li>
                <li>Tests spécifiques par produit</li>
                <li>Tri et décompte des défauts</li>
                <li>Vérification de l'emballage et de l'étiquetage</li>
            </ul>
            <br/>

            <strong>4. Remise du rapport:</strong> un rapport détaillé d'inspection des denrées alimentaires avec des photographies vous sera envoyé le jour même, vous permettant de prendre une décision éclairée concernant l'envoi de votre lot.
            ]]>
            </subtext4>
        <subtext5title>Pourquoi effectuer une inspection des denrées alimentaires ?</subtext5title>
        <subtext5><![CDATA[
            <ul class="marginzero">
                <li>Pour préserver la qualité et la sécurité de vos produits alimentaires à chaque étape</li>
                <li>Pour identifier tout dommage potentiel pendant le transport</li>
                <li>Pour maintenir la confiance des consommateurs et la réputation de la marque</li>
                <li>Pour éviter les rappels liés à la salubrité</li>
                <li>Pour se conformer aux règlements et aux normes de votre marché de destination</li>
            </ul>
            ]]></subtext5>
        <whyUsTitle>Why AsiaInspection</whyUsTitle>
        <whyUsList>
            <li><![CDATA[${{priceIA}} USD all-inclusive per man-day]]></li>
            <li><![CDATA[An inspector onsite within 48 hours<sup class="hoverText" cargo="txtAuditor"><a href="javascript://">[1]</a></sup> and same day reports<sup class="hoverText" cargo="txtSameDayAudit"><a href="javascript://">[2]</a></sup>]]></li>
            <li>Easy online scheduling with customizable checklists</li>
        </whyUsList>
        <hoverOne>
            <![CDATA[AsiaInspection guarantees to have an inspector or auditor ready to be at the factory within 48 hours.<br /><br />This timeframe does not, however, guarantee factory preparedness or cooperation with AsiaInspection. Nor does it guarantee against limiting factors out of the control of AsiaInspection, such as transportation delays, or any event considered an Act of God.]]>
        </hoverOne>
        <hoverTwo>
            80% of all audit reports are delivered the same day. Reports being delivered the same day are contingent upon full factory cooperation.
        </hoverTwo>
        <schedButton url="/register">Get Started</schedButton>
    </fr>

    <de>
        <title>Lebensmittelinspektionen</title>
        <subtext>
            <![CDATA[
            <p class="pwhite">AsiaInspection ist ein weltweiter Anbieter von Inspektionsdiensten und hilft Ihnen, die Qualität und die Sicherheit Ihrer Lebensmittelprodukte zu gewährleisten, bevor sie die Fabrik verlassen.</p>
            ]]>
        </subtext>
        <subtext2title>Lebensmittelinspektionen</subtext2title>
        <subtext2>
            <![CDATA[
            <p>In einer Welt, in der Lebensmittelprodukte oftmals Tausende von Kilometern reisen, um zum Verbraucher zu gelangen, ist in jeder Phase die Gewährleistung der Qualität und der Sicherheit Ihrer Lebensmittel von höchster Bedeutung. Durch fachgerechte Lebensmittelinspektionen erhalten Sie ein wirklichkeitsgetreues Bild über den Zustand Ihres Produktes vor dem Versand und bei der Ankunft am Zielort.</p>
            <p>Die von AI durchgeführten Lebensmittelinspektionen ermöglichen es Ihnen, Unvereinbarkeiten in Ihren Fertigungslosen zu erkennen, bevor sie den landwirtschaftlichen Betrieb oder die Fabrik verlassen, um rechtzeitig zu reagieren und kostenintensive Nachbesserungen, Aussortierungen oder Rückrufaktionen zu vermeiden.  Auf der Grundlage der am selben Tag gelieferten detaillierten Inspektionsberichte und einer Echtzeit-Datenintelligenz hinsichtlich Ihrer Lieferanten können Sie schnelle und fundierte Entscheidungen für Ihre Lebensmittellieferkette treffen.</p>]]
        </subtext2>
        <subtext3title>Lebensmittelinspektionskompetenz</subtext3title>
        <subtext3>
            <![CDATA[
            AI bietet schnelle und zuverlässige Produktinspektionsdienste in den folgenden Kategorien an:<br/>
            <table border="0" width="100%">
                <tr>
                    <td width="50%">
                        <ul style="margin:0px;">
                            <li><a href="/testing/seafood">Fisch & Meeresfrüchte</a>, <a href="/testing/meat-poultry">Fleisch & Geflügel</a></li>
                            <li><a href="/testing/produce-inspections-and-quality-control">Frischprodukte</a></li>
                        </ul>
                    </td>
                    <td width="50%">
                        <ul style="margin:0px;">
                            <li><a href="/testing/quality-control-for-processed-food">Verarbeitete Lebensmittel</a></li>
                            <li><a href="/testing/food-packaging-and-containers">Lebensmittelbehälter</a></li>
                        </ul>
                    </td>
                </tr>
            </table><br/>
            Sobald Ihr Produkt für die Inspektion zur Verfügung steht, besucht einer der spezialisierten AI-Inspektoren Ihren Lieferanten und prüft die Menge, die Verpackung, die Kennzeichnung, die Abmessungen, das Gewicht und die visuellen Eigenschaften eines nach dem Zufallsprinzip ausgewählten Produktmusters. Bei unseren Inspektionen folgen wir den Richtlinien des Lebensmittelcodes der Weltgesundheitsorganisation und verwenden das international anerkannte statistische Stichprobenverfahren gemäß ANSI/ASQC Z1.4 (ISO 2859-1). Dadurch wird gewährleistet, dass wir ein Muster prüfen, das Ihrem tatsächlichen Lebensmittelfertigungslos entspricht, und nicht ein Muster, dessen Prüfung von Ihrem Lieferanten gewünscht wird.
            <br/><br/>
            Unsere Produktinspektoren verfügen über eine umfassende Berufserfahrung in ihren jeweiligen Fachbereichen. Diese umfassen <a href="/testing/produce-inspections-and-quality-control">Frischprodukte</a>, <a href="/testing/quality-control-for-processed-food">verarbeitete Lebensmittel</a>, <a href="/testing/food-packaging-and-containers">Lebensmittelbehälter</a>, <a href="/testing/seafood">Fisch & Meeresfrüchte</a>, <a href="/testing/meat-poultry">Fleisch</a>, <a href="/testing/meat-poultry">Geflügel</a> und andere.  Die Inspektionen erfolgen unter Anwendung der von unseren Experten erstellten detaillierten Inspektionsprotokolle.  Die von AI erstellten Inspektionsprotokolle für Lebensmittel schließen Ihre Anweisungen und Spezifikationen sowie die Industriestandards und unser vielseitiges Know-how ein, so dass eine umfassende Prüfung hinsichtlich der Qualität, der Sicherheit und der Konformität Ihres Lebensmittelproduktes gewährleistet wird.
            ]]>
        </subtext2>
        <subtext4title>Lebensmittelinspektionsverfahren</subtext4title>
        <subtext4>
            <![CDATA[
            <strong>1. Buchung:</strong>  Über Ihren Online-Account oder die <a href="/app">AI mobile app</a>, können Sie Ihre Lebensmittelinspektion schnell und bequem buchen. Unsere benutzerfreundlichen Buchungsformulare führen Sie durch den Prozess und stellen sicher, dass sie alle wesentlichen Angaben Ihres Auftrags enthalten, wie z. B.:
            <ul class="marginzero">
                <li>Detaillierte Kontaktdaten der Fabrik</li>
                <li>Produktbeschreibung</li>
                <li>Bildmaterial</li>
                <li>Die wesentlichen vor Ort durchzuführenden Prüfungen</li>
                <li>Fehler, auf die besonders zu achten ist</li>
                <li>Stichprobenverfahren</li>
            </ul>
            <p>Sofort nach Ihrer Auftragserteilung erhalten Sie ein Preisangebot für Ihre Lebensmittelinspektion.</p>
            <br/>

            <strong>2. Abwicklung:</strong> Unser Team nimmt Kontakt mit Ihrem Lieferanten auf, um das Datum und den Ort der Inspektion zu bestätigen, während unsere Experten ein umfassendes Lebensmittelinspektionsprotokoll für unseren Inspektor erstellen.
            <br/><br/>
            <p>Sie haben Ihre Pläne geändert? Kein Problem: Sie können Ihren Auftrag bis spätestens 16 Uhr am Vortag der geplanten Inspektion ändern oder stornieren.</p>
            <br/>

            <p><strong>3. Inspektion:</strong> Am Tag der Lebensmittelinspektion besucht ein AI-Inspektor das Werk Ihres Lieferanten und führt die folgenden standardisierten Schritte aus:</p>
            <ul class="marginzero">
                <li>Stichprobe nach dem Zufallsprinzip (je nach Art des Produktes)</li>
                <li>Sichtprüfung</li>
                <li>Produktspezifische Prüfungen</li>
                <li>Sortieren und Zählen der Fehler</li>
                <li>Prüfung der Verpackung und der Kennzeichnung</li>
            </ul>
            <br/>

            <strong>4. Lieferung des Berichtes: </strong>  Noch am selben Tag wird Ihnen ein detaillierter Lebensmittelinspektionsbericht mit Fotos zugestellt, der es Ihnen ermöglicht,  eine fundierte Entscheidung hinsichtlich des Versands Ihres Loses zu treffen.
            ]]>
            </subtext4>
        <subtext5title>Wozu dient das Durchführen einer Lebensmittelinspektion?</subtext5title>
        <subtext5><![CDATA[
            <ul class="marginzero">
                <li>Zur Gewährleistung der Qualität und der Sicherheit Ihres Lebensmittelproduktes in jeder Phase</li>
                <li>Zur Identifizierung eines eventuellen Schadens während des Transits</li>
                <li>Zur Aufrechterhaltung  des Vertrauens der Verbraucher und des Markenimages</li>
                <li>Zur Vermeidung von Rückrufaktionen</li>
                <li>Zur Gewährleistung der Konformität mit den gesetzlichen Vorschriften und Normen Ihres Zielmarktes</li>
            </ul>
            ]]></subtext5>
        <whyUsTitle>Why AsiaInspection</whyUsTitle>
        <whyUsList>
            <li><![CDATA[${{priceIA}} USD all-inclusive per man-day]]></li>
            <li><![CDATA[An inspector onsite within 48 hours<sup class="hoverText" cargo="txtAuditor"><a href="javascript://">[1]</a></sup> and same day reports<sup class="hoverText" cargo="txtSameDayAudit"><a href="javascript://">[2]</a></sup>]]></li>
            <li>Easy online scheduling with customizable checklists</li>
        </whyUsList>
        <hoverOne>
            <![CDATA[AsiaInspection guarantees to have an inspector or auditor ready to be at the factory within 48 hours.<br /><br />This timeframe does not, however, guarantee factory preparedness or cooperation with AsiaInspection. Nor does it guarantee against limiting factors out of the control of AsiaInspection, such as transportation delays, or any event considered an Act of God.]]>
        </hoverOne>
        <hoverTwo>
            80% of all audit reports are delivered the same day. Reports being delivered the same day are contingent upon full factory cooperation.
        </hoverTwo>
        <schedButton url="/register">Get Started</schedButton>
    </de>

    <es>
        <title>Inspecciones alimentarias</title>
        <subtext>
            <![CDATA[
            <p class="pwhite">AsiaInspection ofrece servicios de inspección alimentaria a nivel mundial, permitiéndole garantizar la calidad y seguridad de sus productos alimenticios antes de salir de la fábrica.</p>
            ]]>
        </subtext>
        <subtext2title>Inspecciones alimentarias</subtext2title>
        <subtext2>
            <![CDATA[
            <p>En un mundo en que, a menudo, los productos alimenticios viajan miles de kilómetros antes de llegar al consumidor, proteger la calidad y seguridad de los alimentos en todas las etapas resulta fundamental. Las inspecciones alimentarias profesionales le dan una imagen precisa del estado de su producto tanto antes de enviarlo como a su llegada al destino.</p>
            <p>Las inspecciones alimentarias de AI permiten detectar inconsistencias en sus lotes de producción antes de salir de la granja o la fábrica, lo que le permite reaccionar a tiempo y evitar costosas reelaboraciones, reclasificaciones o retiradas de productos. Si recibe informes detallados el mismo día de la inspección y dispone de información de inteligencia de sus proveedores en tiempo real, puede tomar decisiones rápidas e informadas para su cadena de suministro de alimentos.</p>]]
        </subtext2>
        <subtext3title>Expertos en inspecciones alimentarias</subtext3title>
        <subtext3>
            <![CDATA[
            AI ofrece servicios rápidos y fiables de inspección de productos en las siguientes categorías:<br/>
            <table border="0" width="100%">
                <tr>
                    <td width="50%">
                        <ul style="margin:0px;">
                            <li><a href="/testing/seafood">Marisco</a>, <a href="/testing/meat-poultry">carne y aves de corral</a></li>
                            <li><a href="/testing/produce-inspections-and-quality-control">Productos frescos</a></li>
                        </ul>
                    </td>
                    <td width="50%">
                        <ul style="margin:0px;">
                            <li><a href="/testing/quality-control-for-processed-food">Alimentos procesados</a></li>
                            <li><a href="/testing/food-packaging-and-containers">Envases de alimentos</a></li>
                        </ul>
                    </td>
                </tr>
            </table><br/>
            Cuando el producto está listo para su inspección, uno de los inspectores profesionales de AI visitará a su proveedor y comprobará la cantidad, el embalaje, el etiquetado, las dimensiones, el peso y las características visuales de una muestra seleccionada al azar. En nuestros análisis, seguimos las directrices del Código de los Alimentos de la Organización Mundial de la Salud y usamos el procedimiento de muestreo estadístico internacionalmente reconocido ANSI/ASQC Z1.4 (ISO 2859-1). De este modo, comprobamos una muestra que representa adecuadamente su lote de producción de alimentos, y no otra que su proveedor quiera verificar en concreto.
            <br/><br/>
            Nuestros inspectores de productos tienen una gran experiencia en sus respectivas áreas de especialización,  que incluyen <a href="/testing/produce-inspections-and-quality-control">productos frescos</a>, <a href="/testing/quality-control-for-processed-food">alimentos procesados</a>, <a href="/testing/food-packaging-and-containers">envases de alimentos</a>, <a href="/testing/seafood">marisco</a>, <a href="/testing/meat-poultry">carne</a>, y aves <a href="/testing/meat-poultry">de corral</a>, entre otros. Durante las inspecciones, siguen detallados protocolos de inspección preparados por nuestros propios expertos. Los protocolos de inspección alimentaria de AI combinan sus instrucciones y especificaciones con las normas de la industria y nuestra amplia base de conocimientos, garantizando una verificación completa de la calidad, la seguridad y el cumplimiento normativo de sus productos alimenticios.
            ]]>
        </subtext2>
        <subtext4title>El proceso de inspección alimentaria</subtext4title>
        <subtext4>
            <![CDATA[
            <strong>1. Reserva:</strong> mediante su cuenta en línea o la aplicación móvil de AI, puede reservar su inspección alimentaria de forma rápida y sencilla. Nuestro formulario de reserva es fácil de usar y le guiará a través del proceso, asegurándose de incluir todas las especificaciones clave de su pedido, como:
            <br/>
            <ul class="marginzero">
                <li>Información de contacto de la fábrica</li>
                <li>Descripción del producto</li>
                <li>Imágenes</li>
                <li>Pruebas clave para realizar in situ</li>
                <li>Defectos que buscar</li>
                <li>Método de muestreo</li>
            </ul>
            <p>Recibirá un presupuesto para su inspección alimentaria inmediatamente después de realizar su pedido.</p>
            <br/>

            <strong>2. Procesamiento:</strong>  nuestro equipo se pondrá en contacto con su proveedor para confirmar la fecha y el lugar de la inspección, mientras nuestros expertos preparan el protocolo de inspección alimentaria completo que nuestro inspector deberá seguir.
            <br/><br/>
            <p>¿Cambio de planes? No es un problema: puede reprogramar o cancelar su pedido hasta las 16:00 del día previo a la inspección.</p>
            <br/>

            <p><strong>3. Inspección:</strong> el día de la inspección alimentaria, un inspector de AI visitará las instalaciones de su proveedor y ejecutará controles estandarizados como:</p>
            <ul class="marginzero">
                <li>Muestreo aleatorio (determinado según el tipo de producto)</li>
                <li>Revisión visual</li>
                <li>Pruebas específicas del producto</li>
                <li>Clasificación y recuento de defectos</li>
                <li>Comprobación de envasado y etiquetado</li>
            </ul>
            <br/>

            <strong>4. Entrega del informe:</strong> se le enviará un detallado informe de inspección de los alimentos, con fotografías, el mismo día de la inspección, lo que le permitirá tomar una decisión informada en relación con el envío de su lote.
            ]]>
            </subtext4>
        <subtext5title>¿Por qué realizar una inspección alimentaria?</subtext5title>
        <subtext5><![CDATA[
            <ul class="marginzero">
                <li>Para garantizar la calidad y la seguridad de sus productos alimentarios en todas las etapas</li>
                <li>Para identificar posibles daños durante el tránsito</li>
                <li>Para mantener la confianza del consumidor y la reputación de su marca</li>
                <li>Para evitar retiradas de seguridad</li>
                <li>Para cumplir con las regulaciones y normas estatutarias de su mercado objetivo</li>
            </ul>
            ]]></subtext5>
        <whyUsTitle>Why AsiaInspection</whyUsTitle>
        <whyUsList>
            <li><![CDATA[${{priceIA}} USD all-inclusive per man-day]]></li>
            <li><![CDATA[An inspector onsite within 48 hours<sup class="hoverText" cargo="txtAuditor"><a href="javascript://">[1]</a></sup> and same day reports<sup class="hoverText" cargo="txtSameDayAudit"><a href="javascript://">[2]</a></sup>]]></li>
            <li>Easy online scheduling with customizable checklists</li>
        </whyUsList>
        <hoverOne>
            <![CDATA[AsiaInspection guarantees to have an inspector or auditor ready to be at the factory within 48 hours.<br /><br />This timeframe does not, however, guarantee factory preparedness or cooperation with AsiaInspection. Nor does it guarantee against limiting factors out of the control of AsiaInspection, such as transportation delays, or any event considered an Act of God.]]>
        </hoverOne>
        <hoverTwo>
            80% of all audit reports are delivered the same day. Reports being delivered the same day are contingent upon full factory cooperation.
        </hoverTwo>
        <schedButton url="/register">Get Started</schedButton>
    </es>

    <zh>
        <title>食品检验</title>
        <subtext>
            <![CDATA[
            <p class="pwhite">AI亚检在全球范围内提供食品检验服务，帮您确保食品出厂前的质量和安全。</p>
            ]]>
        </subtext>
        <subtext2title>Food Inspections &amp; Quality Control</subtext2title>
        <subtext2>
            <![CDATA[
            <p>食品往往需要多环节的运输才能到达消费者手中，因此，保障食品质量与安全在每个环节都至关重要。专业的食品检验可以为您精准呈现食品运输前和到达后的状态。</p>
            <p>AI亚检的食品检验服务可以在产品离开农场或工厂前帮您识别同一批产品中的异常产品，方便您及时采取措施，避免因重新制作、挑选甚至召回而造成的高成本。</p>]]>
        </subtext2>
        <subtext3title>专业的食品检验服务</subtext3title>
        <subtext3>
            <![CDATA[
            AI亚检能够在以下方面提供快速可靠的检验服务：<br/>
            <table border="0" width="100%">
                <tr>
                    <td width="50%">
                        <ul style="margin:0px;">
                            <li><a href="/testing/seafood">海鲜</a>, <a href="/testing/meat-poultry">肉类和禽类</a></li>
                            <li><a href="/testing/produce-inspections-and-quality-control">新鲜农产品</a></li>
                        </ul>
                    </td>
                    <td width="50%">
                        <ul style="margin:0px;">
                            <li><a href="/testing/quality-control-for-processed-food">加工食品</a></li>
                            <li><a href="/testing/food-packaging-and-containers">包装、储存食品的容器</a></li>
                        </ul>
                    </td>
                </tr>
            </table><br/>
            当您的产品准备就绪后，AI亚检将会派专业检验员赶赴供应商处，检验随机挑选样本的数量、包装、标签、尺寸、重量及外观特征。我们的检验符合世界卫生组织食品法典的有关规定，并采取国际承认的ANSI/ASQC Z1.4 (ISO 2859-1)统计采样程序，保障选取的样本能够合理代表整批产品，而非供应商希望受检的样本。
            <br/><br/>
            AI亚检的产品检验员在各自的专业领域中具有丰富的经验, 涵盖<a href="/testing/produce-inspections-and-quality-control">新鲜农产品</a>, <a href="/testing/quality-control-for-processed-food">加工食品</a>, <a href="/testing/food-packaging-and-containers">包装、储存食品的容器</a>, <a href="/testing/seafood">海鲜</a>, <a href="/testing/meat-poultry">肉类</a>, 和 <a href="/testing/meat-poultry">肉类和禽类</a>等多个领域. 检验员在检查过程中将遵从专家详细制定的检验规范. AI亚检的食品检验规范将客户的要求与行业标准以及过去的经验进行有机结合，保证全面检查食品质量、安全和合规性。
            ]]>
        </subtext3>
        <subtext4title>食品检验流程</subtext4title>
        <subtext4>
            <![CDATA[
            <strong>1. 预约：</strong> 登录网站或使用AI亚检移动应用客户端进行预约，简单迅速。我们的预约登记表简单明了，将在整个预约过程中为您提供指导，保障您在提交订单时提供所有关键的信息，包括：
            <br/>
            <ul class="marginzero">
                <li>工厂联系方式</li>
                <li>产品介绍</li>
                <li>照片</li>
                <li>需要现场开展的重要测试</li>
                <li>需要识别的问题</li>
                <li>取样方法</li>
            </ul>
            <p>在提交订单后，您将会马上收到我们的食品检验报价。</p>
            <br/>

            <strong>2.  处理：</strong> 我们的团队将会与您的供应商联系，确定检验的时间和地点，同时专家将会准备详细的食品检验规范，供检验员参考。
            <br/><br/>
            <p>计划有变？没有问题。在检验前一天的下午4点前，您可以随时重新预约或取消订单。</p>
            <br/>

            <p><strong>3. 检验：</strong> AI亚检将会派出一名检验员在检验当天赴供应商处进行检查，并采取以下标准化步骤：</p>
            <ul class="marginzero">
                <li>随机取样（根据产品类别决定）</li>
                <li>外观检查</li>
                <li>根据产品类型开展特定测试</li>
                <li>识别并统计问题</li>
                <li>检查包装和标签</li>
            </ul>
            <br/>

            <strong>4. 出具报告：</strong> 我们会在当天出具一份详细的食品检验报告，并附有照片，为您的产品配送安排提供信息。
            ]]>
            </subtext4>
        <subtext5title>为什么要开展食品检验？</subtext5title>
        <subtext5><![CDATA[
            <ul class="marginzero">
                <li>保障食品在各个阶段的质量和安全</li>
                <li>鉴定运送过程中可能出现的损失</li>
                <li>保障消费者信心及品牌口碑</li>
                <li>避免安全性召回</li>
                <li>保障遵守目的地市场的法规及标准</li>
            </ul>
            ]]></subtext5>
        <whyUsTitle>为什么选择AI亚检</whyUsTitle>
        <whyUsList>
            <li><![CDATA[${{priceIA}} USD all-inclusive per man-day]]></li>
            <li><![CDATA[An inspector onsite within 48 hours<sup class="hoverText" cargo="txtAuditor"><a href="javascript://">[1]</a></sup> and same day reports<sup class="hoverText" cargo="txtSameDayAudit"><a href="javascript://">[2]</a></sup>]]></li>
            <li>Easy online scheduling with customizable checklists</li>
        </whyUsList>
        <hoverOne>
            <![CDATA[AsiaInspection guarantees to have an inspector or auditor ready to be at the factory within 48 hours.<br /><br />This timeframe does not, however, guarantee factory preparedness or cooperation with AsiaInspection. Nor does it guarantee against limiting factors out of the control of AsiaInspection, such as transportation delays, or any event considered an Act of God.]]>
        </hoverOne>
        <hoverTwo>
            80% of all audit reports are delivered the same day. Reports being delivered the same day are contingent upon full factory cooperation.
        </hoverTwo>
        <schedButton url="/register">Get Started</schedButton>
    </zh>
    
    <tr>
        <title>Gıda Muayene Hizmetleri</title>
        <subtext>
            <![CDATA[
            <p class="pwhite">AsiaInspection ürünlerinizin fabrikadan çıkmadan önce kalite ve güvenliğini sağlamanıza yardımcı olarak, global çapta gıda muayene hizmetleri sunmaktadır.</p>
            ]]>
        </subtext>
        <subtext2title>Gıda Muayeneleri &amp; Quality Control</subtext2title>
        <subtext2>
            <![CDATA[
            <p>Goda ürünlerinin tüketiciye ulaşmadan önce binlerde kilometre yol aldığı bir dünyada gıdanızın kalite ve güvenliğinin korunması her kademede en önemli unsurdur. Profesyonel gıda muayeneleri siz sevkıyattan öncesi kadar hedef noktaya varışında da ürününüzün doğru resmini verir.</p>
            <p>AI gıda muayeneleri zamanında reaksiyon göstermeniz ve maliyetli yeniden işleme, tasnifleme ya da geri çağırmaları önlemenize yardımcı olarak üretim partileriniz çiftlik ya da fabrikadan çıkmadan önce tutarsızlıkları tespit etmenizi sağlamaktadır. Aynı gün teslim edilen detaylı muayene raporları ve tedarikçileriniz hakkında gerçek zamanlı veri istihbaratı ile gıda tedarik zinciriniz için hızlı ve bilinçli kararlar alabilirsiniz.</p>]]>
        </subtext2>
        <subtext3title>Gıda Muayene Ekspertizi</subtext3title>
        <subtext3>
            <![CDATA[
            AI aşağıdaki kategorilerde hızlı ve güvenilir ürün muayene hizmetleri sunar:<br/>
            <table border="0" width="100%">
                <tr>
                    <td width="50%">
                        <ul style="margin:0px;">
                            <li><a href="/testing/seafood">Deniz ürünler</a>, <a href="/testing/meat-poultry"> et ve kümes hayvanları</a></li>
                            <li><a href="/testing/produce-inspections-and-quality-control">Taze mahsul</a></li>
                        </ul>
                    </td>
                    <td width="50%">
                        <ul style="margin:0px;">
                            <li><a href="/testing/quality-control-for-processed-food">İşlenmiş gıda</a></li>
                            <li><a href="/testing/food-packaging-and-containers">Gıda konteynerleri</a></li>
                        </ul>
                    </td>
                </tr>
            </table><br/>
            Ürününüz muayeneye hazır olduğunda, AI'nin profesyonel denetçilerinden biri tedarikçinizi ziyaret edecek ve rastgele seçilmiş numunenin miktar, paketleme, etiketleme, boyut, ağırlık ve görsel niteliklerini kontrol edecektir. Muayenelerimizde, Deny Sağlık Örgütü Gıda Kanunu'nun kurallarını ve uluslararası olarak tanınmış ANSI/ASQC Z1.4 (ISO 2859-1) istatiksel numune alma prosedürünü takip ediyoruz. Bu tedarikçinizin kontrol ettirmek istediği değil, gıda üretim partinizi doğru şekilde yansıtan bir numune kontrolü yapmamızı garantiliyor.
            <br/><br/>
            Our product inspectors are highly experienced in their respective areas of specialization, which include <a href="/testing/produce-inspections-and-quality-control">Taze mahsul</a>, <a href="/testing/quality-control-for-processed-food">İşlenmiş Gıdalar</a>, <a href="/testing/food-packaging-and-containers">Gıda konteynerleri</a>, <a href="/testing/seafood">Deniz ürünü</a>, <a href="/testing/meat-poultry"> Et ve Kümes Hayvanları</a> ve diğerlerini de içeren kendi uzmanlık alanlarında oldukça fazla deneyime sahiplerdir. Muayeneler sırasında, uzmanlarımız tarafından hazırlanana detaylı muayene protokollerini izlerler. AI gıda muayene protokolleri gıda ürünlerinizin kalite, güvenlik ve uygunluklarının kapsamlı bir kontrolünü garantiye alarak, talimat ve şartnamelerinizi endüstri standartlarıyla bir araya getirir.
            ]]>
        </subtext3>
        <subtext4title>Gıda Muayeneleri Süreci</subtext4title>
        <subtext4>
            <![CDATA[
            <strong>1. Kayıt:</strong> AI mobil uygulamasını ya da çevrimiçi hesabınızı kullanarak, gıda muayenesi kaydınızı hızlı ve kolay bir şekilde yapabilirsiniz. Kullanıcı dostu kayıt formlarımız aşağıdaki gibi siparişinizin tüm önemli niteliklerini dahil ettiğinizden emin olmanız için süreç boyunca size yol gösterecektir:
            <br/>
            <ul class="marginzero">
                <li>Fabrika iletişim bilgileri</li>
                <li>Ürün açıklaması</li>
                <li>Resimler</li>
                <li>Sahada yapılacak temel testler</li>
                <li>Araştırılacak kusurlar</li>
                <li>Numune alma metodu</li>
            </ul>
            <p>Siparişinizi verdikten hemen sonra, gıda muayeneniz için bir fiyat teklifi alacaksınız.</p>
            <br/>

            <strong>2. İşleme:</strong> uzmanlarımız denetçimizin izleyeceği kapsamlı bir muayene protokolü hazırlarken, ekibimiz muayene tarih ve yerini onaylamak için tedarikçinizle birlikte hareket edecektir.
            <br/><br/>
            <p>Planlar mı değişti? Sorun değil: muayeneden önceki gün saat 16:00'a kadar siparişinizi yeniden planlayabilir ya da iptal edebilirsiniz.</p>
            <br/>

            <p><strong>3. Muayene:</strong> gıda muayenesi gününde, bir AI denetçisi tedarikçinizin tesisini ziyaret edecek ve aşağıdaki gibi standartlaştırılmış adımları izleyecektir:</p>
            <ul class="marginzero">
                <li>Rastgele numune alma (ürün türüne göre belirlenen)</li>
                <li>Görsel kontrol</li>
                <li>Ürüne özel testler</li>
                <li>Kusur ayıklama ve sayma</li>
                <li>Paketleme ve etiketleme kontrolü</li>
            </ul>
            <br/>

            <strong>4. Rapor teslimi:</strong> aynı gün size partinizin nakliyesiyle ilgili bilinçli bir karar almanızı sağlayan, fotoğraflar eklenmiş detaylı bir gıda muayene raporu gönderilecektir.
            ]]>
            </subtext4>
        <subtext5title>Neden Gıda Muayenesi Yaptırılmalıdır?</subtext5title>
        <subtext5><![CDATA[
            <ul class="marginzero">
                <li>Gıda ürününüzün her kademede kalite ve güvenliğini sağlamak için</li>
                <li>Taşıma sırasında her türlü potansiyel zararı belirlemek için</li>
                <li>Tüketici güveni ve marka itibarını korumak için</li>
                <li>Güvenlik için geri çağırmaları önlemek için</li>
                <li>Hedef pazarınızdaki kanuni düzenleme ve standartlara uymak için</li>
            </ul>
            ]]></subtext5>
       <whyUsTitle>Neden AsiaInspection</whyUsTitle>
        <whyUsList>
            <li><![CDATA[${{priceIA}} USD Her şey dahil fiyatlandırma]]></li>
            <li><![CDATA[48 seat içinde sahada olan denetçi<sup class="hoverText" cargo="txtAuditor"><a href="javascript://">[1]</a></sup> Aynı gun denetim raporları<sup class="hoverText" cargo="txtSameDayAudit"><a href="javascript://">[2]</a></sup>]]></li>
            <li>Kolay çevrimiçi hizmet düzenlemeleri</li>
        </whyUsList>
        <hoverOne>
            <![CDATA[AsiaInspection guarantees to have an inspector or auditor ready to be at the factory within 48 hours.<br /><br />This timeframe does not, however, guarantee factory preparedness or cooperation with AsiaInspection. Nor does it guarantee against limiting factors out of the control of AsiaInspection, such as transportation delays, or any event considered an Act of God.]]>
        </hoverOne>
        <hoverTwo>
            80% of all audit reports are delivered the same day. Reports being delivered the same day are contingent upon full factory cooperation.
        </hoverTwo>
        <schedButton url="/register">Get Started</schedButton>
    </tr>

    <pt>
        <title>Serviços de inspeção de alimentos</title>
        <subtext>
            <![CDATA[
            <p class="pwhite">A AsiaInspection oferece serviços de inspeção alimentares a nível mundial, permitindo-lhe garantir a qualidade e segurança dos seus produtos alimentares antes de saírem da fábrica.</p>
            ]]>
        </subtext>
        <subtext2title>Inspeções Alimentares</subtext2title>
        <subtext2>
            <![CDATA[
            <p>Num mundo onde os produtos alimentares viajam milhares de quilómetros antes de chegarem ao consumidor, garantir a qualidade e a segurança dos seus alimentos é crucial em cada etapa. As inspeções profissionais alimentares  oferecem-lhe uma imagem precisa do estado dos seus produtos antes de serem enviados e quando chegam ao seu destino.</p>
            <p>As inspeções alimentares da AI permitem-lhe detetar inconsistências nos seus lotes de produção antes de saírem da quinta ou fábrica, ajudando-o a reagir em tempo oportuno e evitar retrabalhos, triagens ou reconvocações dispendiosas. Graças aos relatórios de inspeção detalhados entregues no mesmo dia e com informações em tempo-real, pode tomar decisões rápidas e informadas para a sua cadeira de fornecimento alimentar.</p>]]>
        </subtext2>
        <subtext3title>Experiência na Inspeção Alimentar</subtext3title>
        <subtext3>
            <![CDATA[
            A AI oferece serviços de inspeção de produto rápida e de confiança nas seguintes categorias:<br/>
            <table border="0" width="100%">
                <tr>
                    <td width="50%">
                        <ul style="margin:0px;">
                            <li><a href="/testing/seafood">Marisco</a>, <a href="/testing/meat-poultry">carne e aves de capoeira</a></li>
                            <li><a href="/testing/produce-inspections-and-quality-control">Produtos frescos</a></li>
                        </ul>
                    </td>
                    <td width="50%">
                        <ul style="margin:0px;">
                            <li><a href="/testing/quality-control-for-processed-food">Alimentos processados</a></li>
                            <li><a href="/testing/food-packaging-and-containers">Recipientes Alimentares</a></li>
                        </ul>
                    </td>
                </tr>
            </table><br/>
            Quando o seu produto está pronto a ser inspecionado, um dos inspetores profissionais da AI irão visitar o seu fornecedor e verificar a quantidade, embalagem, rotulagem, dimensões, peso e características visuais de uma amostra selecionada aleatoriamente. Nas nossas inspeções, seguimos as diretrizes do Código Alimentar da Organização de Saúde Mundial (World Health Organization Food Code) e usamos o sistema de amostra estatística reconhecido mundialmente ANSI/ASQC Z1.4 (ISO 2859-1), Isto garante que inspecionamos uma amostra que representa corretamente o seu lote de produção alimentar, e não uma amostra que o seu fornecedor pretende que seja inspecionada.
            <br/><br/>
            Os nossos inspetores de produto são altamente qualificados nas suas áreas respetivas de especialização, que incluem <a href="/testing/produce-inspections-and-quality-control"> Produtos Frescos</a>, <a href="/testing/quality-control-for-processed-food">Alimentos Processados</a>, <a href="/testing/food-packaging-and-containers">Recipientes Alimentares</a>, <a href="/testing/seafood">Marisco</a>, <a href="/testing/meat-poultry">Carne</a>, Aves de <a href="/testing/meat-poultry">Capoeira</a>, entre outros. Durante as inspeções, seguem protocolos de inspeção detalhados preparados pelos nossos especialistas. Os protocolos de inspeção alimentar da AI fundem as suas instruções e especificações com os padrões da indústria e o nosso saber-fazer, assegurando uma inspeção exaustiva da qualidade, segurança e conformidade dos seus produtos alimentares.
            ]]>
        </subtext3>
        <subtext4title>Processo de Inspeções Alimentares</subtext4title>
        <subtext4>
            <![CDATA[
            <strong>1. Reserva:</strong> usando a sua conta online ou a aplicação móvel da AI, pode reservar a sua inspeção alimentar de forma rápida e simples.  O nosso formulário de reserva é fácil de usar e guiá-lo-à através do processo, assegurando-se de que inclui todas as especificações chave do seu pedido, tais como:
            <br/>
            <ul class="marginzero">
                <li>Detalhes de contacto da fábrica</li>
                <li>Descrição do produto</li>
                <li>Imagens</li>
                <li>Testes chave a realizar no local</li>
                <li>Defeitos a procurar</li>
                <li>Método de amostragem</li>
            </ul>
            <p>Receberá um orçamento para a sua inspeção alimentar imediatamente depois de realizar o seu pedido.</p>
            <br/>

            <strong>2. Processamento:</strong> a nossa equipa entrará em contacto com o seu fornecedor de forma a confirmar a data e local da inspeção, enquanto os nossos especialistas preparam o protocolo de inspeção alimentar completo que o nosso inspetor deverá seguir.
            <br/><br/>
            <p>Mudança de planos? Não é problema: pode reprogramar ou cancelar o seu pedido até às 16 h do dia anterior à inspeção.</p>
            <br/>

            <p><strong>3. Inspeção:</strong> no dia da inspeção alimentar, um inspetor da AI visitará as instalações do seu fornecedor e executará passos padrões como:</p>
            <ul class="marginzero">
                <li>Amostras aleatórias (determinadas segundo o tipo de produto)</li>
                <li>Inspeção visual</li>
                <li>Testes específicos do produto</li>
                <li>Classificação e contagem dos defeitos</li>
                <li>Inspeção de embalagem e etiquetagem</li>
            </ul>
            <br/>

            <strong>4. Entrega do relatório:</strong> ser-lhe-à enviado um relatório detalhado da inspeção alimentar, com fotografias, no mesmo dia da inspeção, que lhe permitirá tomar uma decisão informada em relação ao envio do seu lote.
            ]]>
            </subtext4>
        <subtext5title>Porquê Realizar uma Inspeção Alimentar?</subtext5title>
        <subtext5><![CDATA[
            <ul class="marginzero">
                <li>Para garantir a qualidade e a segurança dos seus produtos alimentares em todas as etapas</li>
                <li>Para identificar possíveis danos durante o trânsito</li>
                <li>Para manter a confiança do consumidor e a reputação da sua marca</li>
                <li>Para evitar retiradas de segurança</li>
                <li>Para cumprir com as regulações e normas estatuárias do seu mercado de destino</li>
            </ul>
            ]]></subtext5>
        <whyUsTitle>Why AsiaInspection</whyUsTitle>
        <whyUsList>
            <li><![CDATA[${{priceIA}} USD all-inclusive per man-day]]></li>
            <li><![CDATA[An inspector onsite within 48 hours<sup class="hoverText" cargo="txtAuditor"><a href="javascript://">[1]</a></sup> and same day reports<sup class="hoverText" cargo="txtSameDayAudit"><a href="javascript://">[2]</a></sup>]]></li>
            <li>Easy online scheduling with customizable checklists</li>
        </whyUsList>
        <hoverOne>
            <![CDATA[AsiaInspection guarantees to have an inspector or auditor ready to be at the factory within 48 hours.<br /><br />This timeframe does not, however, guarantee factory preparedness or cooperation with AsiaInspection. Nor does it guarantee against limiting factors out of the control of AsiaInspection, such as transportation delays, or any event considered an Act of God.]]>
        </hoverOne>
        <hoverTwo>
            80% of all audit reports are delivered the same day. Reports being delivered the same day are contingent upon full factory cooperation.
        </hoverTwo>
        <schedButton url="/register">Get Started</schedButton>
    </pt>

    <ru>
        <title>Инспекция пищевых товаров</title>
        <subtext>
            <![CDATA[
            <p class="pwhite">AsiaInspection предлагает инспекцию продовольственных товаров по всему миру, помогая вам убедиться в качестве и безопасности ваших продовольственных товаров до того, как они покинут завод.</p>
            ]]>
        </subtext>
        <subtext2title>Food Inspections &amp; Quality Control</subtext2title>
        <subtext2>
            <![CDATA[
            <p>В мире, где пищевые товары часто преодолевают тысячи километров, прежде чем добраться до потребителя, забота о качестве и безопасности продовольствия крайне важна на каждом этапе. Профессиональная продовольственная инспекция покажет точную картину состояния вашей продукции до ее отправки, а также по прибытии в пункт назначения.</p>
            <p>Инспекция пищевых товаров AI позволяет вам выявить несоответствия в партиях продукции, прежде чем она покинет ферму или завод, что даст возможность вовремя отреагировать и избежать дорогостоящей переработки, сортировки или отзыва товара. Благодаря подробным отчетам об инспекции, приходящих в тот же день, и сведениях о ваших поставщиках в реальном времени вы можете принимать быстрые и обоснованные решения, касающиеся вашей цепочки поставок продовольствия.</p>]]>
        </subtext2>
        <subtext3title>Квалифицированная инспекция пищевых товаров</subtext3title>
        <subtext3>
            <![CDATA[
            AI предлагает быструю и заслуживающую доверия инспекцию продовольственных товаров следующих категорий:<br/>
            <table border="0" width="100%">
                <tr>
                    <td width="50%">
                        <ul style="margin:0px;">
                            <li><a href="/testing/seafood">Морепродукты</a>, <a href="/testing/meat-poultry">мясо и птица</a></li>
                            <li><a href="/testing/produce-inspections-and-quality-control">Свежая продукция</a></li>
                        </ul>
                    </td>
                    <td width="50%">
                        <ul style="margin:0px;">
                            <li><a href="/testing/quality-control-for-processed-food">Переработанная пищевая продукция</a></li>
                            <li><a href="/testing/food-packaging-and-containers">Пищевые емкости</a></li>
                        </ul>
                    </td>
                </tr>
            </table><br/>
            Когда ваша продукция готова к инспекции, один из профессиональных инспекторов AI посетит вашего поставщика и проверит качество, упаковку, маркировку, размеры, вес и визуальные характеристики случайно выбранных образцов. Во время инспекции мы следуем рекомендациям Продовольственного кодекса Всемирной Организации Здравоохранения и используем международно признанную процедуру статистической выборки ANSI/ASQC Z1.4 (ISO 2859-1). Это гарантирует, что мы подвергаем проверке образец, который является репрезентативным для данной партии продовольственной продукции, а не тот образец, который ваш поставщик желает подвергнуть проверке.
            <br/><br/>
            Наши инспекторы имеют большой опыт работы в области своей специализации. В их числе: свежая продукция, переработанная пищевая продукция, пищевые емкости, морепродукты, мясо, птица и прочее. Во время инспекции они следуют подробному инспекционному протоколу, разработанному нашими экспертами. Протоколы продовольственных инспекций AI объединяют ваши инструкции и спецификации со стандартами отрасли и нашими обширными знаниями, обеспечивая всеобъемлющую проверку продукции с точки зрения качества, безопасности и соответствия требованиям.
            ]]>
        </subtext3>
        <subtext4title>Технология инспекции пищевых товаров</subtext4title>
        <subtext4>
            <![CDATA[
            <strong>1. Заказ:</strong> с помощью вашей учетной записи онлайн или через мобильное приложение AI вы можете быстро и просто заказать инспекцию пищевых товаров. Благодаря удобным формам для заказа вы без труда разберетесь в процессе и не забудете включить в ваш заказ ключевую информацию, как то:
            <br/>
            <ul class="marginzero">
                <li>Контактная информация завода</li>
                <li>Описание продукции</li>
                <li>Изображения</li>
                <li>Ключевые тесты для проведения на месте</li>
                <li>Искомые дефекты</li>
                <li>Метод выборки</li>
            </ul>
            <p>Вы получите смету для вашей продовольственной инспекции сразу же после размещения заказа.</p>
            <br/>

            <strong>2. Обработка:</strong> наша команда свяжется с вашим поставщиком, чтобы договориться о дате и месте инспекции, пока наши эксперты готовят всеобъемлющий протокол продовольственной инспекции для нашего инспектора.
            <br/><br/>
            <p>Ваши планы поменялись? Нет проблем: вы можете перенести время выполнения заказа или отменить его до 16:00 накануне инспекции.</p>
            <br/>

            <p><strong>3. Инспекция:</strong> в день инспекции пищевых товаров инспектор AI посетит предприятие поставщика и проведет следующие стандартные процедуры:</p>
            <ul class="marginzero">
                <li>Случайная выборка (определяется в соответствии с типом продукции)</li>
                <li>Визуальная проверка</li>
                <li>Тесты в соответствии со спецификой продукции</li>
                <li>Сортировка и подсчет брака</li>
                <li>Проверка упаковки и маркировки</li>
            </ul>
            <br/>

            <strong>4. Доставка отчета:</strong> детальный отчет продовольственной инспекции с фотографиями будет отослан вам в тот же день, позволяя принять обоснованное решение касательно перевозки данной партии товара.
            ]]>
            </subtext4>
        <subtext5title>Зачем проводить инспекцию продовольственных товаров?</subtext5title>
        <subtext5><![CDATA[
            <ul class="marginzero">
                <li>Чтобы обеспечить качество и безопасность ваших пищевых товаров на каждом этапе</li>
                <li>Чтобы выявить потенциальный ущерб во время транспортировки</li>
                <li>Чтобы сохранить доверие потребителей и репутацию бренда</li>
                <li>Чтобы избежать отзыва товара из-за проблем с безопасностью</li>
                <li>Чтобы соответствовать регламентам и стандартам вашего рынка назначения</li>
            </ul>
            ]]></subtext5>
        <whyUsTitle>Why AsiaInspection</whyUsTitle>
        <whyUsList>
            <li><![CDATA[${{priceIA}} USD all-inclusive per man-day]]></li>
            <li><![CDATA[An inspector onsite within 48 hours<sup class="hoverText" cargo="txtAuditor"><a href="javascript://">[1]</a></sup> and same day reports<sup class="hoverText" cargo="txtSameDayAudit"><a href="javascript://">[2]</a></sup>]]></li>
            <li>Easy online scheduling with customizable checklists</li>
        </whyUsList>
        <hoverOne>
            <![CDATA[AsiaInspection guarantees to have an inspector or auditor ready to be at the factory within 48 hours.<br /><br />This timeframe does not, however, guarantee factory preparedness or cooperation with AsiaInspection. Nor does it guarantee against limiting factors out of the control of AsiaInspection, such as transportation delays, or any event considered an Act of God.]]>
        </hoverOne>
        <hoverTwo>
            80% of all audit reports are delivered the same day. Reports being delivered the same day are contingent upon full factory cooperation.
        </hoverTwo>
        <schedButton url="/register">Get Started</schedButton>
    </ru>

    <it>
        <title>Ispezioni Alimentari Services</title>
        <subtext>
            <![CDATA[
            <p class="pwhite">AsiaInspection fornisce servizi di ispezione alimentare a livello globale, per aiutarti a garantire la qualità e la sicurezza dei tuoi prodotti alimentari prima che lascino la fabbrica.</p>
            ]]>
        </subtext>
        <subtext2title>Ispezioni Alimentari &amp; Quality Control</subtext2title>
        <subtext2>
            <![CDATA[
            <p>In un mondo in cui i prodotti alimentari spesso viaggiano per migliaia di chilometri prima di raggiungere il consumatore, salvaguardare la qualità e la sicurezza dei tuoi alimenti è di importanza fondamentale ad ogni stadio. Ispezioni alimentari professionali ti forniscono un quadro preciso dello stato del tuo prodotto prima che venga spedito, così come al suo arrivo a destinazione.</p>
            <p>Le ispezioni alimentari AI ti consentono di individuare eventuali disomogeneità nei tuoi lotti di produzione prima che lascino la fabbrica o l'azienda agricola, mettendoti in condizioni di agire tempestivamente ed evitare costose rilavorazioni, cernite o ritiri dal mercato. Con dettagliati rapporti dell'ispezione inviati il giorno stesso e informazioni in tempo reale sui tuoi fornitori, puoi prendere decisioni rapide e informate sulla tua filiera di produzione e approvvigionamento alimentare.</p>]]>
        </subtext2>
        <subtext3title>Competenza nelle Ispezioni Alimentari</subtext3title>
        <subtext3>
            <![CDATA[
            AI offre servizi di ispezione di prodotto rapidi e affidabili nelle seguenti categorie:<br/>
            <table border="0" width="100%">
                <tr>
                    <td width="50%">
                        <ul style="margin:0px;">
                            <li><a href="/testing/seafood">Pesce</a>, <a href="/testing/meat-poultry">carne e pollame</a></li>
                            <li><a href="/testing/produce-inspections-and-quality-control">Prodotti freschi</a></li>
                        </ul>
                    </td>
                    <td width="50%">
                        <ul style="margin:0px;">
                            <li><a href="/testing/quality-control-for-processed-food">Alimenti industriali</a></li>
                            <li><a href="/testing/food-packaging-and-containers">Contenitori per alimenti</a></li>
                        </ul>
                    </td>
                </tr>
            </table><br/>
            Quando il tuo prodotto è pronto per essere ispezionato, uno degli ispettori professionisti di AI visiterà il tuo fornitore e controllerà il quantitativo contenuto, la confezione, l'etichettatura, le dimensioni, il peso e le caratteristiche visive di un campione selezionato a caso. Nelle nostre ispezioni, seguiamo le linee guida previste dal World Health Organization Food Code e adottiamo la procedura di campionamento statistico ANSI/ASQC Z1.4 (ISO 2859-1), riconosciuta a livello internazionale. Ciò garantisce che selezioniamo un campione che rappresenti in modo appropriato il tuo lotto di produzione, e non un campione che il tuo fornitore vuole che tu controlli.
            <br/><br/>
            I nostri ispettori di prodotto hanno grande esperienza nelle loro rispettive aree di specializzazione, che includono Prodotti Freschi, Alimenti Industriali, Contenitori per Alimenti, Pesce, Carne, Pollame e altri ancora. Durante le ispezioni, seguono dei protocolli dettagliati preparati dai nostri esperti. I protocolli per le ispezioni alimentari di AI uniscono le tue istruzioni e le tue specifiche con gli standard di settore e con il nostro ampio know-how, assicurando un controllo completo della qualità, della sicurezza e della conformità dei tuoi prodotti alimentari.
            ]]>
        </subtext3>
        <subtext4title>Procedura per le Ispezioni Alimentari</subtext4title>
        <subtext4>
            <![CDATA[
            <strong>1. Prenotazione:</strong> utilizzando il tuo account online o l'app mobile AI, puoi prenotare la tua ispezione alimentare in modo semplice e rapido. I nostri intuitivi moduli di prenotazione ti guideranno lungo la procedura, facendo in modo che tu includa tutte le informazioni fondamentali relative al tuo ordine, come:
            <br/>
            <ul class="marginzero">
                <li>Informazioni di contatto della fabbrica</li>
                <li>Descrizione del prodotto</li>
                <li>Immagini</li>
                <li>Test principali da eseguire in loco</li>
                <li>Difetti di cui controllare l'eventuale presenza</li>
                <li>Metodo di campionamento</li>
            </ul>
            <p>Riceverai un preventivo del costo della tua ispezione alimentare subito dopo aver inoltrato l'ordine.</p>
            <br/>

            <strong>2.  Elaborazione:</strong> il nostro team terrà i contatti con il tuo fornitore per confermare la data e il luogo dell'ispezione, mentre i nostri esperti prepareranno un protocollo completo di ispezione alimentare cui il nostro ispettore si atterrà.
            <br/><br/>
            <p>Cambio di piani? Non è un problema: puoi riprogrammare o annullare il tuo ordine fino alle 16.00 del giorno precedente l'ispezione.</p>
            <br/>

            <p><strong>3.  Ispezione:</strong> il giorno dell'ispezione, un ispettore visiterà lo stabilimento del tuo fornitore e seguirà i seguenti passaggi standardizzati:</p>
            <ul class="marginzero">
                <li>Campionamento casuale (scelto a seconda del tipo di prodotto)</li>
                <li>Controllo visivo</li>
                <li>Test di prodotto specifici</li>
                <li>Classificazione e conteggio dei difetti</li>
                <li>Controllo degli imballi e dell'etichettatura</li>
            </ul>
            <br/>

            <strong>4. Consegna del rapporto:</strong> lo stesso giorno ti verrà inviato un dettagliato rapporto dell'ispezione alimentare con tanto di fotografie, così da consentirti di prendere una decisione informata sulla spedizione del tuo lotto.
            ]]>
            </subtext4>
        <subtext5title>Perché eseguire un'Ispezione Alimentare?</subtext5title>
        <subtext5><![CDATA[
            <ul class="marginzero">
                <li>Per salvaguardare la qualità e la sicurezza del tuo prodotto alimentare ad ogni stadio.</li>
                <li>Per identificare qualunque danno potenziale durante il transito</li>
                <li>Per conservare la fiducia del consumatore e tutelare l'immagine del marchio</li>
                <li>Per evitare ritiri dal mercato legati alla sicurezza</li>
                <li>Per ottemperare alle normative regolamentari e agli standard del tuo mercato di destinazione</li>
            </ul>
            ]]></subtext5>
        <whyUsTitle>Perché AsiaInspection</whyUsTitle>
        <whyUsList>
            <li><![CDATA[${{priceIA}} USD tutto compreso per giorno-uomo]]></li>
            <li><![CDATA[An inspector onsite within 48 hours<sup class="hoverText" cargo="txtAuditor"><a href="javascript://">[1]</a></sup> and same day reports<sup class="hoverText" cargo="txtSameDayAudit"><a href="javascript://">[2]</a></sup>]]></li>
            <li>Easy online scheduling with customizable checklists</li>
        </whyUsList>
        <hoverOne>
            <![CDATA[AsiaInspection guarantees to have an inspector or auditor ready to be at the factory within 48 hours.<br /><br />This timeframe does not, however, guarantee factory preparedness or cooperation with AsiaInspection. Nor does it guarantee against limiting factors out of the control of AsiaInspection, such as transportation delays, or any event considered an Act of God.]]>
        </hoverOne>
        <hoverTwo>
            80% of all audit reports are delivered the same day. Reports being delivered the same day are contingent upon full factory cooperation.
        </hoverTwo>
        <schedButton url="/register">Get Started</schedButton>
    </it>

</document>
