<?xml version="1.0" encoding="utf-8"?>
<document>
	<pageMeta>
		<pageTitle>
			<en>Technical Inspection, Audit &amp; Training Services - Mechanical QC | AsiaInspection</en>
			<es>Servicios de control de calidad para piezas textiles | Inspecciones, pruebas de laboratorio, auditorías sociales y de fábricas | AsiaInspection.es</es>
			<zh>机械零部件质量控制服务 | 国际标准检验测试审核认证</zh>
			<fr>Services de contrôle de qualité pour les pièces textiles | Inspections, tests en laboratoire, audits d'usine et audits éthique | AsiaInspection.fr</fr>
			<de>Qualitätssicherung für Bauteile und technische Komponenten</de>
			<it>Servizi di controllo della qualità per componenti tecnici | Ispezioni, test di laboratorio, controlli di fabbriche e audit sociali | AsiaInspection.it</it>
			<ar>خدمات مراقبة جودة أجزاء المنسوجات | عمليات التفتيش والاختبارات المعملية وعمليات التدقيق في المصنع والتدقيق الاجتماعي | AsiaInspection.ae</ar>
			<pt>Serviços de controle de qualidade para bens de peças têxteis | Inspeções, testes laboratoriais, auditoria social e de fábrica | AsiaInspection.com.br</pt>
			<tr>Tekstil Ürünleri Parçaları için Kalite Kontrol Hizmetleri | Denetimler, Laboratuvar Testleri, Fabrika ve Kayıt Teftişleri | AsiaInspection.com.tr</tr>
		</pageTitle>
		<pageDesc>
			<en>AI has teams dedicated specifically to the Technical and Mechanical industry. We offer the highest quality inspection and QC services. Learn more about our audits and inspections here.</en>
			<de>Asia Inspection bietet spezialisierte Inspektoren für die technische und mechanische Industrie. Erfahren Sie hier mehr zu unserer Qualitätssicherung.</de>
			<pt>AI tem equipas especificamente dedicadas à indústria Técnica e Mecânica.  Oferecemos inspeções da mais alta qualidade e serviços de CQ. Saiba mais sobre as nossas auditorias e inspeções aqui.</pt>
		</pageDesc>
	</pageMeta>

	<en>
		<title>Technical Parts</title>
		<subTitle>AI has dedicated teams specifically the Technical &amp; Mechanical Industry. We offer the highest quality inspections &amp; audits by employing engineers and specialists in their respective fields, coupled with in-depth training and strict internal audits.</subTitle>
		<subtext>
			<![CDATA[
			<p>AsiaInspection helps importers of mechanical and technical parts to ensure the precision and quality of their components and goods, as well as to comply with international regulations and the technical specifications required by the client.</p>
			<p>Complete your order 100% online and choose from hundreds of customizable specific product checklists. AsiaInspection guarantees to have a trained mechanical engineering professional in any factory within 48 hours.</p>
			<br /><br />
			]]>
		</subtext>
		<schedButton url="/register">Get Started</schedButton>
		<soloutionTitle>QC Tailored for Mechanical and Technical Parts</soloutionTitle>

		<soloutionContent>
			<![CDATA[
			<p>By using our array of mechanical and technical part checklists, AsiaInspection offers you a unique method of ensuring the quality of your products. We also verify that required international standards are being met, while minimizing risks, improving your efficiency and thus allowing you to reduce costs.</p>


			<h2 >Technical Parts Expertise</h2>

			<p>AI's technical parts expertise helps to ensure safe and quality products including:</p>
			<table border="0" width="100%">
				<tr>
					<td width="50%">
						<ul style="margin:0px;">
							<li>Automotive Parts</li>
							<li>Casting and Forging</li>
							<li>Hydraulic Components</li>
							<li>Machinery</li>
							<li>Metal Components and Assemblies</li>
						</ul>
					</td>
					<td width="50%">
						<ul style="margin:0px;">
							<li>Moulds and Precision Tooling</li>
							<li>Plastic Moulding</li>
							<li>Scrap Metal</li>
							<li>Welding</li>
						</ul>
					</td>
				</tr>
			</table>

			<p style="padding-top:10px;">Diverse tests are performed to check the mechanical performance and properties of products and components, including:</p>
			<table border="0" width="100%">
				<tr>
					<td width="50%">
						<ul style="margin:0px;">
							<li>Destructive or Non-destructive Testing</li>
							<li>Dimensional Inspections</li>
							<li>GO/No GO Check</li>
							<li>Visual Inspection</li>
						</ul>
					</td>
					<td width="50%">
						<ul style="margin:0px;">
							<li>Detect Poor Assemblies &amp; Surface Damage</li>
							<li>Functional Testing</li>
							<li>Welding Inspection</li>
						</ul>
					</td>
				</tr>
			</table>


			<h2 >Lab Testing for the Technical Parts Industry</h2>

			<p>AsiaInspection is accredited to test according to national and international standards. Ensure your product meets technical part standards for your destination market with <a href="/quality-control-services/laboratory-testing">laboratory testing</a> including:</p>
			<table border="0" width="100%">
				<tr>
					<td width="50%">
						<ul style="margin:0px;">
							<li>ASTM</li>
							<li>BSI</li>
							<li>GB</li>
							<li>Material Composition</li>
						</ul>
					</td>
					<td width="50%">
						<ul style="margin:0px;">
							<li>DIN</li>
							<li>Mechanical Properties</li>
							<li>UL</li>
						</ul>
					</td>
				</tr>
			</table>
			]]>
		</soloutionContent>
	</en>

	<ru>
		<title>Технические детали</title>
		<subtext>
			<![CDATA[
			<p>Компания AsiaInspection помогает импортерам механических и технических деталей соответствовать требованиям качества, которые предъявляются к компонентам и товарам, а также международным стандартам и техническим спецификациям.</p>
			<p>Оформите все детали Вашего заказа сайте и выберите из сотен перечней проверки продукции, которые можно модифицировать по Вашему усмотрению. AsiaInspection гарантирует, что через 48 часов на Ваше производство прибудет обученный профессионал в машиностроении.</p>
			<br /><br />
			]]>
		</subtext>
		<schedButton url="/register">Приступить</schedButton>
		<soloutionTitle>Контроль качества механических и технических деталей</soloutionTitle>

		<soloutionContent>
			<![CDATA[
			<p>Компания AsiaInspection предлагает уникальный способ обеспечения качества Ваших товаров с помощью разнообразных перечней проверки механических и технических деталей. Мы также обеспечиваем соответствие международным стандартам, минимизацию рисков и повышение эффективности, что позволяет Вам снизить затраты.</p>


			<h2 >Экспертная оценка технических деталей</h2>

			<p>Экспертная оценка компании AI помогает обеспечить соответствие стандартам качества и безопасности для следующих товаров:</p>
			<table border="0" width="100%">
				<tr>
					<td width="50%">
						<ul style="margin:0px;">
							<li>Автозапчасти</li>
							<li>Литье и ковка</li>
							<li>Гидравлические детали</li>
							<li>Оборудование</li>
							<li>Металлические детали и сборочные детали</li>
						</ul>
					</td>
					<td width="50%">
						<ul style="margin:0px;">
							<li>Литейные формы и прецизионные инструменты</li>
							<li>Литье из пластика</li>
							<li>Металлический лом</li>
							<li>Сварка</li>
						</ul>
					</td>
				</tr>
			</table>

			<p>Для проверки качества и свойств товаров мы выполняем разнообразные тестирования продукции и компонентов:</p>
			<table border="0" width="100%">
				<tr>
					<td width="50%">
						<ul style="margin:0px;">
							<li>Испытание ресурса</li>
							<li>Проверка размеров</li>
							<li>Проверка работоспособности</li>
							<li>Визуальная проверка</li>
						</ul>
					</td>
					<td width="50%">
						<ul style="margin:0px;">
							<li>Обнаружение некачественных сборочных единиц и повреждений поверхности</li>
							<li>Функциональное тестирование</li>
							<li>Проверка сварки</li>
						</ul>
					</td>
				</tr>
			</table>


			<h2 >Лабораторные тестирования технических частей</h2>

			<p>AsiaInspection имеет необходимую аккредитацию для тестирования в соответствии с национальными и международными стандартами. Обеспечьте соответствие Вашей продукции необходимым техническим стандартам с помощью следующих лабораторных тестирований:</p>
			<table border="0" width="100%">
				<tr>
					<td width="50%">
						<ul style="margin:0px;">
							<li>ASTM</li>
							<li>BSI</li>
							<li>GB</li>
							<li>Анализ состава материала</li>
						</ul>
					</td>
					<td width="50%">
						<ul style="margin:0px;">
							<li>DIN</li>
							<li>Механические свойства</li>
							<li>UL</li>
						</ul>
					</td>
				</tr>
			</table>
			]]>
		</soloutionContent>
	</ru>

	<es>
		<title>Piezas técnicas</title>
		<subTitle>AI ha dedicado equipos específicamente a la técnica mecánica e industrial. Ofrecemos las mejores inspecciones y auditorías de calidad mediante el empleo de ingenieros y especialistas en sus respectivos campos, junto con formación en profundidad y estrictas auditorías internas.</subTitle>
		<subtext>
			<![CDATA[
			<p>AsiaInspection ayuda a las empresas importadoras de piezas mecánicas y técnicas a garantizar la precisión y calidad de sus componentes y artículos, así como a cumplir las normativas internacionales y especificaciones técnicas requeridas por el cliente.</p>
			<p>Realice el pedido de forma totalmente electrónica y escoja entre diversos protocolos de inspección personalizables de productos específicos. AsiaInspection garantiza que un profesional formado en ingeniería mecánica visitará su fábrica en un plazo de 48 horas.</p>
			<br /><br />
			]]>
		</subtext>
		<schedButton url="/register">Comenzar</schedButton>
		<soloutionTitle>Controles de calidad diseñados a medida para piezas técnicas y mecánicas</soloutionTitle>

		<soloutionContent>
			<![CDATA[
			<p>Mediante el uso de nuestra gama de listas de verificación de piezas técnicas y mecánicas, AsiaInspection le ofrece un método único para garantizar la calidad de sus productos. También nos encargamos de verificar el cumplimiento de las regulaciones internacionales, al mismo tiempo que reducimos al mínimo los riesgos y mejoramos la eficiencia, reduciendo así los costes.</p>


			<h2 >Experiencia en piezas de aplicación técnica</h2>

			<p>La experiencia en piezas de aplicación técnica de AI garantiza unos productos seguros y de calidad, entre los que se incluyen artículos de los siguientes sectores:</p>
			<table border="0" width="100%">
				<tr>
					<td width="50%">
						<ul style="margin:0px;">
							<li>Piezas de automoción</li>
							<li>Fundición y forja</li>
							<li>Componentes hidráulicos</li>
							<li>Maquinaria</li>
							<li>Componentes y conjuntos metálicos</li>
						</ul>
					</td>
					<td width="50%">
						<ul style="margin:0px;">
							<li>Moldes y herramientas de precisión</li>
							<li>Moldeado de plásticos</li>
							<li>Chatarra</li>
							<li>Soldaduras</li>
						</ul>
					</td>
				</tr>
			</table>
			 <br>
			<p>Se realizan diversas pruebas para comprobar el rendimiento mecánico y las propiedades de los productos y componentes, incluyendo:</p>
			<table border="0" width="100%">
				<tr>
					<td width="50%">
						<ul style="margin:0px;">
							<li>Pruebas destructivas o no destructivas</li>
							<li>Inspecciones dimensionales</li>
							<li>Pruebas de aprobado/fallo</li>
							<li>Inspección visual</li>
						</ul>
					</td>
					<td width="50%">
						<ul style="margin:0px;">
							<li>Detección de errores de ensamblajes y daños en la superficie</li>
							<li>Pruebas funcionales</li>
							<li>Inspección de soldaduras</li>
						</ul>
					</td>
				</tr>
			</table>


			<h2 >Pruebas de laboratorio específicas para el sector de piezas de aplicación técnica</h2>

			<p>AsiaInspection está acreditada para realizar pruebas según las regulaciones nacionales e internacionales. Asegúrese de que su producto cumple las normativas aplicables a las piezas técnicas en el país de destino a través de pruebas de laboratorio que incluyen:</p>
			<table border="0" width="100%">
				<tr>
					<td width="50%">
						<ul style="margin:0px;">
							<li>ASTM</li>
							<li>BSI</li>
							<li>GB</li>
							<li>Composición de materiales</li>
						</ul>
					</td>
					<td width="50%">
						<ul style="margin:0px;">
							<li>DIN</li>
							<li>Propiedades mecánicas</li>
							<li>UL</li>
						</ul>
					</td>
				</tr>
			</table>
			]]>
		</soloutionContent>
	</es>

	<zh>
		<title>技术部件</title>
			<subTitle>AI亚检为技术与机械行业配备了专门的团队。我们提供最高质量的检测和审核，分别聘用相关领域的工程师和专家，并与深入的培训和严格的内部审核相结合。</subTitle>
		<subtext>
			<![CDATA[
			<p>AsiaInspection 帮助机械和技术部件进口商确保其元件和制品的精度和质量，并符合国际法规和客户要求的技术规范。</p>
			<p>100% 在线完成您的订单并从数百个定制产品特定清单中选择。AsiaInspection 保证经过培训的机械工程专业人员在 48 小时内到达工厂。</p>
			<br /><br />
			]]>
		</subtext>
		<schedButton url="/register">咨询详情</schedButton>
		<soloutionTitle>专为机械和技术部件定制的质量控制</soloutionTitle>

		<soloutionContent>
			<![CDATA[
			<p>通过使用我们的一系列机械和技术部件清单，AsiaInspection 向您提供确保产品质量的独特方法。我们还验证是否符合要求的国际标准，规避风险、提高效率，进而降低成本。</p>


			<h2 >技术部件专业知识</h2>

			<p>AI亚检的技术部件专业知识可以帮助确保安全、优质的产品，包括：</p>
			<table border="0" width="100%">
				<tr>
					<td width="50%">
						<ul style="margin:0px;">
							<li>汽车部件</li>
							<li>铸锻</li>
							<li>液压元件</li>
							<li>机械</li>
							<li>金属元件和组件</li>
						</ul>
					</td>
					<td width="50%">
						<ul style="margin:0px;">
							<li>模具和精密工具</li>
							<li>塑胶模具</li>
							<li>废金属</li>
							<li>焊接</li>
						</ul>
					</td>
				</tr>
			</table>

			<p>执行各种测试，检查产品和元件的机械性能和属性，包括：</p>
			<table border="0" width="100%">
				<tr>
					<td width="50%">
						<ul style="margin:0px;">
							<li>破坏性或非破坏性测试</li>
							<li>尺寸检查</li>
							<li>止通检查</li>
							<li>视觉检查</li>
						</ul>
					</td>
					<td width="50%">
						<ul style="margin:0px;">
							<li>检测不良组件和表面破损</li>
							<li>功能测试</li>
							<li>焊接检查</li>
						</ul>
					</td>
				</tr>
			</table>


			<h2 >技术部件行业实验室测试</h2>

			<p>AsiaInspection 具有根据各国标准和国际标准进行测试的资格。通过实验室测试，确保您的产品符合目标市场的技术部件标准，其中包括：</p>
			<table border="0" width="100%">
				<tr>
					<td width="50%">
						<ul style="margin:0px;">
							<li>ASTM</li>
							<li>BSI</li>
							<li>GB</li>
							<li>材料成分</li>
						</ul>
					</td>
					<td width="50%">
						<ul style="margin:0px;">
							<li>DIN</li>
							<li>机械属性</li>
							<li>UL</li>
						</ul>
					</td>
				</tr>
			</table>
			]]>
		</soloutionContent>
	</zh>

	<fr>
		<title>Pièces techniques</title>
		<subTitle>
AI possède des équipes spécialisées dans les pièces mécaniques et techniques. Nous offrons le meilleur des inspections et des audits en envoyant des ingénieurs et des experts dans leur domaine, soutenus par une formation complète et contrôlés par des audits internes stricts.

		</subTitle>
		<schedButton url="/enregistrement">Commencer</schedButton>
		<soloutionTitle>Contrôles qualité spécifiques aux pièces mécaniques et techniques</soloutionTitle>

		<soloutionContent>
			<![CDATA[
			<p>En utilisant notre éventail de checklists pour pièces mécaniques et techniques, AsiaInspection vous offre une méthode unique pour garantir la qualité de vos produits. Nous vérifions également qu'ils sont en conformité avec les normes internationales en vigueur, et que tout en minimisant les risques, ils améliorent votre efficacité et vous permettent ainsi de réduire les coûts.</p>


			<h2 >Expertise sur les pièces techniques</h2>

			<p>L'expertise sur les pièces techniques d'AI contribue à garantir des produits sûrs et de qualité, y compris :</p>
			<table border="0" width="100%">
				<tr>
					<td width="50%">
						<ul style="margin:0px;">
							<li>Pièces automobiles</li>
							<li>Pièces moulées ou forgées</li>
							<li>Composants hydrauliques</li>
							<li>Machines</li>
							<li>Composants métalliques et assemblages</li>
						</ul>
					</td>
					<td width="50%">
						<ul style="margin:0px;">
							<li>Moules et outillage de précision</li>
							<li>Moulages plastique</li>
							<li>Ferraille</li>
							<li>Soudages</li>
						</ul>
					</td>
				</tr>
			</table>

			<p>Des tests divers sont effectués pour vérifier les performances et les propriétés des produits et composants mécaniques, y compris :</p>
			<table border="0" width="100%">
				<tr>
					<td width="50%">
						<ul style="margin:0px;">
							<li>Contrôles destructifs ou non destructifs</li>
							<li>Contrôles de dimensions</li>
							<li>Contrôle de type Feu vert / Feu Rouge</li>
							<li>Inspection visuelle</li>
						</ul>
					</td>
					<td width="50%">
						<ul style="margin:0px;">
							<li>Détection des assemblages défectueux et dommages superficiels</li>
							<li>Tests fonctionnels</li>
							<li>Inspection du soudage</li>
						</ul>
					</td>
				</tr>
			</table>


			<h2 >Tests en laboratoire pour le secteur des pièces techniques</h2>

			<p>AsiaInspection est accrédité pour effectuer des tests conformément aux normes nationales et internationales. Assurez-vous que le produit répond aux normes sur les pièces techniques de votre marché de destination grâce à des tests de laboratoire, y compris :</p>
			<table border="0" width="100%">
				<tr>
					<td width="50%">
						<ul style="margin:0px;">
							<li>ASTM</li>
							<li>BSI</li>
							<li>GB</li>
							<li>Composition du matériau</li>
						</ul>
					</td>
					<td width="50%">
						<ul style="margin:0px;">
							<li>DIN</li>
							<li>Propriétés mécaniques</li>
							<li>UL</li>
						</ul>
					</td>
				</tr>
			</table>
			]]>
		</soloutionContent>
	</fr>

	<de>
		<title>Technische Komponenten</title>
				<subTitle>AI verfügt über spezielle Teams, vor allem in der technischen und &amp; Maschinenbauindustrie. Wir bieten Kontrollen in höchster Qualität &amp; Wirtschaftsprüfungen durch einstellende Ingenieure und Experten in den jeweiligen Bereichen, in Verbindung mit fundierten Schulungen und strengen internen Prüfungen.</subTitle>
		<subtext>
			<![CDATA[
			<p>AsiaInspection hilft Importeuren von mechanischen und technischen Komponenten, die genaue Funktion und Qualität der Komponenten und Waren sicherzustellen. Außerdem wird gewährleistet, dass internationale Normen und die technischen Spezifikationen, die der Kunde erfüllen muss, eingehalten werden.</p>
			<p>Schließen Sie Ihre Bestellung komplett online ab und wählen Sie aus Hunderten von anpassbaren Produktprüflisten. AsiaInspection garantiert Ihnen, dass sich innerhalb von 48 Stunden ein geschulter Maschinenbauexperte im gewünschten Werk einfindet.</p>
			<br /><br />
			]]>
		</subtext>
		<schedButton url="/registrieren">Erste Schritte</schedButton>
		<soloutionTitle>Qualitätskontrolle speziell für mechanische und technische Teile</soloutionTitle>

		<soloutionContent>
			<![CDATA[
			<p>Durch den Einsatz unserer Prüflisten für mechanische und technische Teile bieten wir Ihnen eine einzigartige Methode zur Sicherstellung der Qualität Ihrer Produkte. Wir stellen zudem sicher, dass die erforderlichen internationalen Normen erfüllt werden, und sorgen dafür, dass Risiken minimiert werden, Ihre Effizienz steigt und Ihre Kosten entsprechend sinken.</p>


			<h2 >Fachwissen zu technischen Komponenten</h2>

			<p>Mit dem Fachwissen von AI in Bezug auf technische Komponenten können Sie sicherstellen, dass Ihre Produkte sicher und qualitativ hochwertig sind, darunter:</p>
			<table border="0" width="100%">
				<tr>
					<td width="50%">
						<ul style="margin:0px;">
							<li>Automobilteile</li>
							<li>Gießen und Formen</li>
							<li>Hydraulische Komponenten</li>
							<li>Maschinen</li>
							<li>Metallkomponenten &amp; -baugruppen</li>
						</ul>
					</td>
					<td width="50%">
						<ul style="margin:0px;">
							<li>Gussformen &amp; Präzisionswerkzeuge</li>
							<li>Kunststoffspritzguss</li>
							<li>Altmetall</li>
							<li>Geschweißte Produkte</li>
						</ul>
					</td>
				</tr>
			</table>

			<p>Es werden verschiedene Prüfungen durchgeführt, um die mechanische Leistung und die Eigenschaften der Produkte und Komponenten zu ermitteln. Dazu gehören die folgenden Prüfungen:</p>
			<table border="0" width="100%">
				<tr>
					<td width="50%">
						<ul style="margin:0px;">
							<li>Zerstörende oder zerstörungsfreie Prüfung</li>
							<li>Maßprüfungen</li>
							<li>Go/No Go-Belastungsprüfung</li>
							<li>Sichtprüfung</li>
						</ul>
					</td>
					<td width="50%">
						<ul style="margin:0px;">
							<li>Erkennung von mangelhaften Baugruppen und Oberflächenschäden</li>
							<li>Funktionsprüfungen</li>
							<li>Schweißprüfung</li>
						</ul>
					</td>
				</tr>
			</table>


			<h2 >Labortest für technische Komponenten</h2>

			<p>AsiaInspection verfügt über die nötigen Zulassungen, um Prüfungen nach nationalen und internationalen Normen durchzuführen. Mithilfe von Labortests sorgen Sie dafür, dass Ihr Produkt die auf dem Zielmarkt geltenden Normen für technische Komponenten erfüllt, darunter:</p>
			<table border="0" width="100%">
				<tr>
					<td width="50%">
						<ul style="margin:0px;">
							<li>ASTM</li>
							<li>BSI</li>
							<li>GB</li>
							<li>Materialzusammensetzung</li>
						</ul>
					</td>
					<td width="50%">
						<ul style="margin:0px;">
							<li>DIN</li>
							<li>Mechanische Eigenschaften</li>
							<li>UL</li>
						</ul>
					</td>
				</tr>
			</table>
			]]>
		</soloutionContent>
	</de>

	<it>
		<title>Componenti tecnici</title>
		<subtext>
			<![CDATA[
			<p>AsiaInspection consente agli importatori di parti meccaniche e tecniche di garantire la precisione e la qualità di articoli e componenti, nonché a conformarsi alle norme internazionali e alle specifiche tecniche richieste dal cliente.</p>
			<p>Puoi completare l'ordine online e scegliere tra centinaia di liste di controllo personalizzabili e specifiche per i prodotti. AsiaInspection garantisce che un esperto qualificato nel settore dell'ingegneria meccanica verrà inviato in fabbrica entro 48 ore.</p>
			<br /><br />
			]]>
		</subtext>
		<schedButton url="/register">Inizia ora</schedButton>
		<soloutionTitle>Controllo della qualità su misura per componenti tecnici e meccanici</soloutionTitle>

		<soloutionContent>
			<![CDATA[
			<p>Utilizzando una vasta gamma di liste di controllo per componenti tecnici e meccanici, AsiaInspection offre un metodo esclusivo per garantire la qualità dei tuoi prodotti. Inoltre verifichiamo che vengano rispettati gli standard internazionali, riducendo al minimo i rischi, migliorando l'efficienza e permettendo quindi di ridurre i costi.</p>


			<h2 >Competenza nel settore dei componenti tecnici</h2>

			<p>Le competenze di AI nel settore dei componenti tecnici contribuiscono a garantire la sicurezza e la qualità dei prodotti, tra cui:</p>
			<table border="0" width="100%">
				<tr>
					<td width="50%">
						<ul style="margin:0px;">
							<li>Parti di autoveicoli</li>
							<li>Articoli per colate e forgiature</li>
							<li>Componenti idraulici</li>
							<li>Macchinari</li>
							<li>Componenti e gruppi metallici</li>
						</ul>
					</td>
					<td width="50%">
						<ul style="margin:0px;">
							<li>Stampi e utensili di precisione</li>
							<li>Formatura plastica</li>
							<li>Rottami metallici</li>
							<li>Saldature</li>
						</ul>
					</td>
				</tr>
			</table>

			<p>Diversi test vengono effettuati per verificare le proprietà e le prestazioni meccaniche di prodotti e componenti, tra cui:</p>
			<table border="0" width="100%">
				<tr>
					<td width="50%">
						<ul style="margin:0px;">
							<li>Test distruttivi o non distruttive</li>
							<li>Controlli dimensionali</li>
							<li>Verifica GO/No GO</li>
							<li>Ispezione visiva</li>
						</ul>
					</td>
					<td width="50%">
						<ul style="margin:0px;">
							<li>Rilevazione di gruppi metallici di scarsa qualità e danni alla superficie</li>
							<li>Test funzionali</li>
							<li>Ispezione della saldatura</li>
						</ul>
					</td>
				</tr>
			</table>


			<h2 >Test di laboratorio per il settore dei componenti tecnici</h2>

			<p>AsiaInspection è accreditata per eseguire test secondo standard nazionali e internazionali. Assicurati che il tuo prodotto soddisfi gli standard del settore dei componenti tecnici per il mercato di destinazione con le nostre prove di laboratorio, tra cui:</p>
			<table border="0" width="100%">
				<tr>
					<td width="50%">
						<ul style="margin:0px;">
							<li>ASTM</li>
							<li>BSI</li>
							<li>GB</li>
							<li>Composizione materiale</li>
						</ul>
					</td>
					<td width="50%">
						<ul style="margin:0px;">
							<li>DIN</li>
							<li>Proprietà meccaniche</li>
							<li>UL</li>
						</ul>
					</td>
				</tr>
			</table>
			]]>
		</soloutionContent>
	</it>

	<ar>
		<title>الأجزاء التقنية</title>
		<subtext>
			<![CDATA[
			<p>تساعد AsiaInspection مستوردي الأجزاء الميكانيكية والتقنية على ضمان دقة المكونات والبضائع وجودتها، فضلاً عن التوافق مع الأنظمة الدولية والمواصفات التقنية المطلوبة من العميل.</p>
			<p>أكمل طلبك عبر الإنترنت بالكامل، واختر من قوائم تدقيق مئات المنتجات القابلة للتخصيص. تضمن AsiaInspection توفير متخصص مدرّب في الهندسة الميكانيكية في أي مصنع خلال 48 ساعة.</p>
			<br /><br />
			]]>
		</subtext>
		<schedButton url="/register">بدء الاستخدام</schedButton>
		<soloutionTitle>مراقبة الجودة المخصصة للأجزاء التقنية والميكانيكية</soloutionTitle>

		<soloutionContent>
			<![CDATA[
			<p>باستخدام مجموعتنا من قوائم تدقيق الأجزاء الميكانيكية والتقنية، تقدم AsiaInspection طريقة فريدة لضمان جودة منتجاتك. كما نتحقق من التوافق مع المعايير الدولية المطلوبة، مع تقليل المخاطر وتحسين مستوى كفاءتك، ما يسمح لك بالحد من التكاليف.</p>


			<h2 >خبرة الأجزاء التقنية</h2>

			<p>تساعد خبرة AI في الأجزاء التقنية على ضمان سلامة وجودة منتجات تتضمن:</p>
			<table border="0" width="100%">
				<tr>
					<td width="50%">
						<ul style="margin:0px;">
							<li>قطع غيار السيارات</li>
							<li>السبك والحدادة</li>
							<li>المكونات الهيدروليكية</li>
							<li>الآليات</li>
							<li>المكونات المعدنية والتركيبات</li>
						</ul>
					</td>
					<td width="50%">
						<ul style="margin:0px;">
							<li>القوالب والأدوات الدقيقة</li>
							<li>القوالب البلاستيكية</li>
							<li>الخردة المعدنية</li>
							<li>اللحام</li>
						</ul>
					</td>
				</tr>
			</table>

			<p>تُجرى اختبارات متنوعة للتحقق من الأداء والخصائص الميكانيكية للمنتجات والمكونات، بما في ذلك:</p>
			<table border="0" width="100%">
				<tr>
					<td width="50%">
						<ul style="margin:0px;">
							<li>الاختبار الإتلافي أو غير الإتلافي</li>
							<li>التفتيش البعدي</li>
							<li>اختبار النجاح/ الرسوب</li>
							<li>التفتيش البصري</li>
						</ul>
					</td>
					<td width="50%">
						<ul style="margin:0px;">
							<li>الكشف عن تركيبات ضعيفة وأضرار سطحية</li>
							<li>الاختبار الوظيفي</li>
							<li>تفتيش تلحيم المعادن</li>
						</ul>
					</td>
				</tr>
			</table>


			<h2 >الاختبارات المعملية لقطاع الأجزاء التقنية</h2>

			<p>شركة AsiaInspection معتمدة لإجراء الاختبارات وفقاً للمعايير الوطنية والدولية. نتأكد من توافق منتجك مع معايير الأجزاء التقنية الخاصة بالسوق الوجهة من خلال الاختبارات المعملية، بما في ذلك:</p>
			<table border="0" width="100%">
				<tr>
					<td width="50%">
						<ul style="margin:0px;">
							<li>الجمعية الأمريكية للمهندسين الميكانيكيين (ASME)</li>
							<li>معهد المعايير البريطانية (BSI)</li>
							<li>GB</li>
							<li>تركيب المواد</li>
						</ul>
					</td>
					<td width="50%">
						<ul style="margin:0px;">
							<li>الجمعية الأمريكية لاختبار المواد (ASTM)</li>
							<li>DIN</li>
							<li>الخصائص الميكانيكية</li>
							<li>UL</li>
						</ul>
					</td>
				</tr>
			</table>
			]]>
		</soloutionContent>
	</ar>

	<pt>
		<title>Peças técnicas</title>
		<subtext>
			<![CDATA[
			<p>AsiaInspection ajuda aos importadores de peças mecânicas e técnicas a garantir a precisão e a qualidade de seus componentes e produtos e em conformidade com as regulamentações internacionais e especificações técnicas exigidas pelo cliente.</p>
			<p>Faça seu pedido 100% online e escolha entre centenas de listas de verificação personalizáveis de produtos específicos. AsiaInspection garante ter um profissional de engenharia mecânica treinado em qualquer fábrica dentro de 48 horas.</p>
			<br /><br />
			]]>
		</subtext>
		<schedButton url="/register">Introdução</schedButton>
		<soloutionTitle>Controle de qualidade para as peças mecânicas e técnicas</soloutionTitle>

		<soloutionContent>
			<![CDATA[
			<p>Utilizando nossa variedade de listas de verificação de peças mecânicas e técnicas, a AsiaInspection oferece a você um método único para garantir a qualidade de seus produtos. Também verificamos se os padrões internacionais exigidos estão sendo cumpridos e, enquanto os riscos são minimizados, melhoramos sua eficiência e possibilitamos a redução de custos para sua empresa.</p>


			<h2 >Conhecimento das peças técnicas</h2>

			<p>O conhecimento da AI nas peças técnicas ajuda a garantir a segurança e a qualidade dos produtos, incluindo:</p>
			<table border="0" width="100%">
				<tr>
					<td width="50%">
						<ul style="margin:0px;">
							<li>Peças automotivas</li>
							<li>Fundição</li>
							<li>Componentes hidráulicos</li>
							<li>Maquinaria</li>
							<li>Componentes de metal e de montagem</li>
						</ul>
					</td>
					<td width="50%">
						<ul style="margin:0px;">
							<li>Moldes e ferramentas de precisão</li>
							<li>Moldagem de plástico</li>
							<li>Sucata de metal</li>
							<li>Soldagem</li>
						</ul>
					</td>
				</tr>
			</table>

			<p>Diversos testes são realizados para verificar o desempenho mecânico e as propriedades de produtos e componentes, incluindo:</p>
			<table border="0" width="100%">
				<tr>
					<td width="50%">
						<ul style="margin:0px;">
							<li>Testes destrutivos e não destrutivos</li>
							<li>Inspeções das dimensões</li>
							<li>Verificações GO/Não GO</li>
							<li>Inspeção Visual</li>
						</ul>
					</td>
					<td width="50%">
						<ul style="margin:0px;">
							<li>Detecção de montagem mal realizada e danos na superfície</li>
							<li>Testes funcionais</li>
							<li>Inspeção de soldagem</li>
						</ul>
					</td>
				</tr>
			</table>


			<h2 >Testes laboratoriais para a indústria de peças técnicas</h2>

			<p>A AsiaInspection está capacitada para a realização de testes de acordo com padrões nacionais e internacionais. Garanta que o seu produto atingirá os padrões para peças técnicas de seu mercado de destino, com testes laboratoriais incluindo:</p>
			<table border="0" width="100%">
				<tr>
					<td width="50%">
						<ul style="margin:0px;">
							<li>ASTM</li>
							<li>BSI</li>
							<li>GB</li>
							<li>Análise de composição do material</li>
						</ul>
					</td>
					<td width="50%">
						<ul style="margin:0px;">
							<li>DIN</li>
							<li>Propriedades mecânicas</li>
							<li>UL</li>
						</ul>
					</td>
				</tr>
			</table>
			]]>
		</soloutionContent>
	</pt>

	<tr>
		<title>Teknik Parçalar</title>
		<subtext>
			<![CDATA[
			<p>AsiaInspection, mekanik ve teknik parça ithalatçılarının bileşenlerinin ve ürünlerinin doğruluğu ve kalitesini sağlamasına ve müşteri tarafından zorunlu tutulan uluslararası düzenlemelere ve teknik ürün özelliklerine uymasına yardımcı olur.</p>
			<p>Siparişinizi tamamen çevrimiçi olarak gerçekleştirin ve yüzlerce özelleştirilebilir özel ürün kontrol listesi arasından seçim yapın. AsiaInspection, fabrikanıza 48 saat içinde eğitimli bir makine mühendisliği uzmanı sağlamayı garanti eder.</p>
			<br /><br />
			]]>
		</subtext>
		<schedButton url="/register">Başlayın</schedButton>
		<soloutionTitle>Mekanik ve Teknik Parçalar için Özel Olarak Tasarlanmış Kalite Kontrol</soloutionTitle>

		<soloutionContent>
			<![CDATA[
			<p>AsiaInspection çeşitli mekanik ve teknik parça kontrol listelerimizi kullanarak size ürünlerinizin kalitesini sağlamanın benzersiz bir yöntemini sunar. Aynı zamanda riskleri minimuma düşürüyor ve verimliliğinizi artırırken uluslararası standartları karşılamanızı sağlıyor ve böylece maliyetleri azaltmanıza yardımcı oluyoruz.</p>


			<h2 >Teknik Parça Uzmanlığı</h2>

			<p>AI'nin teknik parça alanındaki uzmanlığı şu alanlarda ürünlerinizin güvenilirliğini ve kalitesini sağlamanıza yardımcı olur:</p>
			<table border="0" width="100%">
				<tr>
					<td width="50%">
						<ul style="margin:0px;">
							<li>Otomotiv Parçaları</li>
							<li>Döküm ve Dövme</li>
							<li>Hidrolik Bileşenler</li>
							<li>Makineler</li>
							<li>Metal Bileşenler ve Düzenekler</li>
						</ul>
					</td>
					<td width="50%">
						<ul style="margin:0px;">
							<li>Kalıplar ve Hassas Alet Üretimi</li>
							<li>Plastik Kalıplar</li>
							<li>Hurda Metal</li>
							<li>Kaynak İşlemi</li>
						</ul>
					</td>
				</tr>
			</table>

			<p>Mekanik performansı ve ürün ve bileşenlerin özelliklerini incelemek için şunları içeren çeşitli testler gerçekleştirilir:</p>
			<table border="0" width="100%">
				<tr>
					<td width="50%">
						<ul style="margin:0px;">
							<li>Tahribatlı veya Tahribatsız Testler</li>
							<li>Boyut Denetimleri</li>
							<li>GO Kontrollü/GO Kontrolsüz</li>
							<li>Görsel Denetim</li>
						</ul>
					</td>
					<td width="50%">
						<ul style="margin:0px;">
							<li>Zayıf Montajları ve Yüzey Hasarlarını Belirleme</li>
							<li>İşlevsel Testler</li>
							<li>Kaynak İşlemi Denetimleri</li>
						</ul>
					</td>
				</tr>
			</table>


			<h2 >Teknik Parça Endüstrisi için Laboratuvar Testleri</h2>

			<p>AsiaInspection, ulusal ve uluslararası standartlara göre test yapma yetkisine sahiptir. Şunları kapsayan laboratuvar testleriyle ürününüzün hedef pazarınızın tüm teknik parça standartlarıyla uyumluluğunu sağlayın:</p>
			<table border="0" width="100%">
				<tr>
					<td width="50%">
						<ul style="margin:0px;">
							<li>ASTM</li>
							<li>BSI</li>
							<li>GB</li>
							<li>Madde Yapısı</li>
						</ul>
					</td>
					<td width="50%">
						<ul style="margin:0px;">
							<li>DIN</li>
							<li>Mekanik Özellikler</li>
							<li>UL</li>
						</ul>
					</td>
				</tr>
			</table>
			]]>
		</soloutionContent>
	</tr>

</document>
